Workbook

Sheet 00_Cover
B2: Northline Consumer Products
B3: Monthly KPI scorecard · ops + finance · actual vs target with RAG
B4: FY2026 monthly · 12 KPIs · fictional CPG company
B6: What this file is
B7: A twelve-month operating and finance scorecard for a fictional mid-size CPG company. Targets and RAG thresholds live on Assumptions; monthly actuals are inputs; the scorecard, YTD, trends, and dashboard are formulas (Green / Amber / Red).
B9: How to use
B10: 1. Edit yellow cells on 01_Assumptions (KPI targets, direction H/L/R, amber/green bands, reporting month).
B11: 2. Paste or type monthly actuals on 02_Actuals (yellow).
B12: 3. Read actual vs target, variance, and RAG on 03_Scorecard — nothing on that tab is hardcoded.
B13: 4. Read MoM, rolling 3-month, YTD, and vs-target trends on 04_Trends.
B14: 5. Use 05_Dashboard as the one-pager (traffic-light tiles + charts).
B16: File conventions
... B23: https://github.com/saisiri-bandaru

Sheet 01_Assumptions
B2: Assumptions
B3: Yellow + blue = inputs. Targets, direction, and RAG bands drive the scorecard.
B5: Reporting month (1 = Jan-26 … 12 = Dec-26) | C5: 9 | D5: =INDEX({"Jan-26","Feb-26","Mar-26","Apr-26","May-26","Jun-26","Jul-26","Aug-26","Sep-26","Oct-26","Nov-26","Dec-26"},1,C5) | E5: Scorecard as-of and dashboard INDEX to this month. Sample is parked in Sep so YTD is visible.
B7: RAG rules
B8: H (higher-better): Green if actual ≥ target; Amber if actual ≥ target × (1 − amber band); else Red.
B9: L (lower-better): Green if actual ≤ target; Amber if actual ≤ target × (1 + amber band); else Red.
B10: R (range, e.g. headcount): Green if |actual/target − 1| ≤ green band; Amber if ≤ amber band; else Red.
B12: KPI register
B13: KPI | C13: Unit | D13: Direction (H/L/R) | E13: Amber band | F13: Green band (R) | G13: Aggregation | H13: Polarity
B14: Net revenue | C14: $000s | D14: H | E14: 0.03 | F14: 0.02 | G14: SUM | H14: Higher is better
B15: Gross margin % | C15: % | D15: H | E15: 0.015 | F15: 0.008 | G15: AVG | H15: Higher is better
B16: EBITDA | C16: $000s | D16: H | E16: 0.05 | F16: 0.02 | G16: SUM | H16: Higher is better
B17: Volume | C17: 000 cases | D17: H | E17: 0.03 | F17: 0.02 | G17: SUM | H17: Higher is better
B18: OTIF % | C18: % | D18: H | E18: 0.02 | F18: 0.01 | G18: AVG | H18: Higher is better
B19: Scrap % | C19: % | D19: L | E19: 0.15 | F19: 0.05 | G19: AVG | H19: Lower is better
B20: DSO | C20: days | D20: L | E20: 0.08 | F20: 0.03 | G20: LAST | H20: Lower is better
B21: CCC | C21: days | D21: L | E21: 0.08 | F21: 0.03 | G21: LAST | H21: Lower is better
B22: Headcount | C22: FTE | D22: R | E22: 0.03 | F22: 0.015 | G22: LAST | H22: Hit the plan (range)
B23: Attrition % (ann.) | C23: % | D23: L | E23: 0.15 | F23: 0.05 | G23: AVG | H23: Lower is better
B24: Operating cash flow | C24: $000s | D24: H | E24: 0.1 | F24: 0.04 | G24: SUM | H24: Higher is better
B25: SG&A % of sales | C25: % | D25: L | E25: 0.04 | F25: 0.015 | G25: AVG | H25: Lower is better
B27: Monthly targets — FY2026 (inputs)
C28: Jan-26 | D28: Feb-26 | E28: Mar-26 | F28: Apr-26 | G28: May-26 | H28: Jun-26 | I28: Jul-26 | J28: Aug-26 | K28: Sep-26 | L28: Oct-26 | M28: Nov-26 | N28: Dec-26 | O28: FY26
B29: Net revenue | C29: 71000 | D29: 68000 | E29: 73500 | F29: 75000 | G29: 77500 | H29: 79000 | I29: 80500 | J29: 79800 | K29: 77200 | L29: 82000 | M29: 87500 | N29: 94000 | O29: =SUM(C29:N29)
B30: Gross margin % | C30: 0.422 | D30: 0.422 | E30: 0.424 | F30: 0.425 | G30: 0.426 | H30: 0.427 | I30: 0.427 | J30: 0.426 | K30: 0.425 | L30: 0.428 | M30: 0.43 | N30: 0.432 | O30: =AVERAGE(C30:N30)
B31: EBITDA | C31: 10295 | D31: 9860 | E31: 10658 | F31: 10875 | G31: 11238 | H31: 11455 | I31: 11672 | J31: 11571 | K31: 11194 | L31: 11890 | M31: 12688 | N31: 13630 | O31: =SUM(C31:N31)
B32: Volume | C32: 5917 | D32: 5667 | E32: 6125 | F32: 6250 | G32: 6458 | H32: 6583 | I32: 6708 | J32: 6650 | K32: 6433 | L32: 6833 | M32: 7292 | N32: 7833 | O32: =SUM(C32:N32)
B33: OTIF % | C33: 0.97 | D33: 0.97 | E33: 0.97 | F33: 0.97 | G33: 0.97 | H33: 0.97 | I33: 0.97 | J33: 0.97 | K33: 0.97 | L33: 0.97 | M33: 0.97 | N33: 0.97 | O33: =AVERAGE(C33:N33)
B34: Scrap % | C34: 0.018 | D34: 0.018 | E34: 0.018 | F34: 0.018 | G34: 0.018 | H34: 0.018 | I34: 0.018 | J34: 0.018 | K34: 0.018 | L34: 0.018 | M34: 0.018 | N34: 0.018 | O34: =AVERAGE(C34:N34)
B35: DSO | C35: 42 | D35: 42 | E35: 42 | F35: 42 | G35: 42 | H35: 42 | I35: 42 | J35: 42 | K35: 42 | L35: 42 | M35: 42 | N35: 42 | O35: =N35
B36: CCC | C36: 62 | D36: 62 | E36: 62 | F36: 62 | G36: 62 | H36: 62 | I36: 62 | J36: 62 | K36: 62 | L36: 62 | M36: 62 | N36: 62 | O36: =N36
B37: Headcount | C37: 286.5 | D37: 287.8 | E37: 289.2 | F37: 291 | G37: 292.4 | H37: 294.1 | I37: 297 | J37: 298.4 | K37: 299.1 | L37: 302.3 | M37: 303.5 | N37: 304.8 | O37: =N37
B38: Attrition % (ann.) | C38: 0.12 | D38: 0.12 | E38: 0.12 | F38: 0.12 | G38: 0.12 | H38: 0.12 | I38: 0.12 | J38: 0.12 | K38: 0.12 | L38: 0.12 | M38: 0.12 | N38: 0.12 | O38: =AVERAGE(C38:N38)
B39: Operating cash flow | C39: 5680 | D39: 5440 | E39: 5880 | F39: 6000 | G39: 6200 | H39: 6320 | I39: 6440 | J39: 6384 | K39: 6176 | L39: 6560 | M39: 7000 | N39: 7520 | O39: =SUM(C39:N39)
B40: SG&A % of sales | C40: 0.185 | D40: 0.185 | E40: 0.185 | F40: 0.185 | G40: 0.185 | H40: 0.185 | I40: 0.185 | J40: 0.185 | K40: 0.185 | L40: 0.185 | M40: 0.185 | N40: 0.185 | O40: =AVERAGE(C40:N40)
B42: FY25 actuals (for YoY on Trends) — revenue and volume only
C43: Jan-26 | D43: Feb-26 | E43: Mar-26 | F43: Apr-26 | G43: May-26 | H43: Jun-26 | I43: Jul-26 | J43: Aug-26 | K43: Sep-26 | L43: Oct-26 | M43: Nov-26 | N43: Dec-26 | O43: FY25
B44: Net revenue FY25 | C44: 66000 | D44: 64000 | E44: 69000 | F44: 70500 | G44: 72000 | H44: 73500 | I44: 75000 | J44: 74200 | K44: 72800 | L44: 76000 | M44: 80500 | N44: 87000 | O44: =SUM(C44:N44)
B45: Volume FY25 | C45: 5500 | D45: 5333 | E45: 5750 | F45: 5875 | G45: 6000 | H45: 6125 | I45: 6250 | J45: 6183 | K45: 6067 | L45: 6333 | M45: 6708 | N45: 7250 | O45: =SUM(C45:N45)
B47: Aggregation: SUM for flow KPIs (revenue, EBITDA, volume, cash). AVG for rates. LAST for stocks (DSO, CCC, headcount).

Sheet 02_Actuals
B2: Monthly actuals — FY2026
B3: Yellow + blue = inputs. Paste a new month here; scorecard, trends, and dashboard recalculate.
B5: Actuals
C6: Jan-26 | D6: Feb-26 | E6: Mar-26 | F6: Apr-26 | G6: May-26 | H6: Jun-26 | I6: Jul-26 | J6: Aug-26 | K6: Sep-26 | L6: Oct-26 | M6: Nov-26 | N6: Dec-26 | O6: FY26
B7: Net revenue | C7: 70200 | D7: 67400 | E7: 74100 | F7: 73800 | G7: 78200 | H7: 80100 | I7: 79800 | J7: 80500 | K7: 76500 | L7: 83400 | M7: 89200 | N7: 95800 | O7: =SUM(C7:N7)
B8: Gross margin % | C8: 0.418 | D8: 0.415 | E8: 0.422 | F8: 0.425 | G8: 0.428 | H8: 0.43 | I8: 0.427 | J8: 0.424 | K8: 0.421 | L8: 0.426 | M8: 0.432 | N8: 0.435 | O8: =AVERAGE(C8:N8)
B9: EBITDA | C9: 9688 | D9: 9166 | E9: 10670 | F9: 10849 | G9: 11652 | H9: 12095 | I9: 11651 | J9: 11511 | K9: 10786 | L9: 12343 | M9: 13558 | N9: 14753 | O9: =SUM(C9:N9)
B10: Volume | C10: 5792 | D10: 5532 | E10: 6237 | F10: 6027 | G10: 6614 | H10: 6808 | I10: 6584 | J10: 6775 | K10: 6279 | L10: 7089 | M10: 7619 | N10: 8223 | O10: =SUM(C10:N10)
B11: OTIF % | C11: 0.962 | D11: 0.951 | E11: 0.974 | F11: 0.978 | G11: 0.969 | H11: 0.975 | I11: 0.948 | J11: 0.961 | K11: 0.97 | L11: 0.976 | M11: 0.981 | N11: 0.964 | O11: =AVERAGE(C11:N11)
B12: Scrap % | C12: 0.021 | D12: 0.024 | E12: 0.019 | F12: 0.017 | G12: 0.018 | H12: 0.016 | I12: 0.022 | J12: 0.02 | K12: 0.019 | L12: 0.017 | M12: 0.015 | N12: 0.016 | O12: =AVERAGE(C12:N12)
B13: DSO | C13: 44.2 | D13: 45.1 | E13: 43.6 | F13: 42.9 | G13: 41.4 | H13: 42.1 | I13: 43 | J13: 44.2 | K13: 42.5 | L13: 41.2 | M13: 40 | N13: 41.6 | O13: =N13
B14: CCC | C14: 68.5 | D14: 69.3 | E14: 64.9 | F14: 62 | G14: 58.6 | H14: 59.9 | I14: 62.6 | J14: 65.2 | K14: 63.3 | L14: 58 | M14: 52.6 | N14: 54.6 | O14: =N14
B15: Headcount | C15: 286.5 | D15: 285.9 | E15: 288.4 | F15: 289.6 | G15: 291.8 | H15: 292.5 | I15: 295.6 | J15: 296.8 | K15: 297.9 | L15: 300.7 | M15: 302.8 | N15: 304.1 | O15: =N15
B16: Attrition % (ann.) | C16: 0.118 | D16: 0.152 | E16: 0.109 | F16: 0.101 | G16: 0.097 | H16: 0.141 | I16: 0.112 | J16: 0.134 | K16: 0.108 | L16: 0.099 | M16: 0.095 | N16: 0.102 | O16: =AVERAGE(C16:N16)
B17: Operating cash flow | C17: 5100 | D17: 4200 | E17: 6800 | F17: 5900 | G17: 7400 | H17: 7100 | I17: 5600 | J17: 6200 | K17: 4800 | L17: 7900 | M17: 9100 | N17: 8600 | O17: =SUM(C17:N17)
B18: SG&A % of sales | C18: 0.191 | D18: 0.194 | E18: 0.186 | F18: 0.184 | G18: 0.181 | H18: 0.179 | I18: 0.188 | J18: 0.187 | K18: 0.19 | L18: 0.182 | M18: 0.178 | N18: 0.176 | O18: =AVERAGE(C18:N18)
B20: YTD (through reporting month) — formulas
B21: KPI | C21: YTD actual | D21: YTD target | E21: YTD var | F21: Aggregation
B22: Net revenue | C22: =SUM(OFFSET(C7,0,0,1,'01_Assumptions'!$C$5)) | D22: =SUM(OFFSET('01_Assumptions'!C29,0,0,1,'01_Assumptions'!$C$5)) | E22: =C22-D22 | F22: SUM
B23: Gross margin % | C23: =AVERAGE(OFFSET(C8,0,0,1,'01_Assumptions'!$C$5)) | D23: =AVERAGE(OFFSET('01_Assumptions'!C30,0,0,1,'01_Assumptions'!$C$5)) | E23: =C23-D23 | F23: AVG
B24: EBITDA | C24: =SUM(OFFSET(C9,0,0,1,'01_Assumptions'!$C$5)) | D24: =SUM(OFFSET('01_Assumptions'!C31,0,0,1,'01_Assumptions'!$C$5)) | E24: =C24-D24 | F24: SUM
B25: Volume | C25: =SUM(OFFSET(C10,0,0,1,'01_Assumptions'!$C$5)) | D25: =SUM(OFFSET('01_Assumptions'!C32,0,0,1,'01_Assumptions'!$C$5)) | E25: =C25-D25 | F25: SUM
B26: OTIF % | C26: =AVERAGE(OFFSET(C11,0,0,1,'01_Assumptions'!$C$5)) | D26: =AVERAGE(OFFSET('01_Assumptions'!C33,0,0,1,'01_Assumptions'!$C$5)) | E26: =C26-D26 | F26: AVG
B27: Scrap % | C27: =AVERAGE(OFFSET(C12,0,0,1,'01_Assumptions'!$C$5)) | D27: =AVERAGE(OFFSET('01_Assumptions'!C34,0,0,1,'01_Assumptions'!$C$5)) | E27: =C27-D27 | F27: AVG
B28: DSO | C28: =INDEX(C13:N13,1,'01_Assumptions'!$C$5) | D28: =INDEX('01_Assumptions'!C35:N35,1,'01_Assumptions'!$C$5) | E28: =C28-D28 | F28: LAST
B29: CCC | C29: =INDEX(C14:N14,1,'01_Assumptions'!$C$5) | D29: =INDEX('01_Assumptions'!C36:N36,1,'01_Assumptions'!$C$5) | E29: =C29-D29 | F29: LAST
B30: Headcount | C30: =INDEX(C15:N15,1,'01_Assumptions'!$C$5) | D30: =INDEX('01_Assumptions'!C37:N37,1,'01_Assumptions'!$C$5) | E30: =C30-D30 | F30: LAST
B31: Attrition % (ann.) | C31: =AVERAGE(OFFSET(C16,0,0,1,'01_Assumptions'!$C$5)) | D31: =AVERAGE(OFFSET('01_Assumptions'!C38,0,0,1,'01_Assumptions'!$C$5)) | E31: =C31-D31 | F31: AVG
B32: Operating cash flow | C32: =SUM(OFFSET(C17,0,0,1,'01_Assumptions'!$C$5)) | D32: =SUM(OFFSET('01_Assumptions'!C39,0,0,1,'01_Assumptions'!$C$5)) | E32: =C32-D32 | F32: SUM
B33: SG&A % of sales | C33: =AVERAGE(OFFSET(C18,0,0,1,'01_Assumptions'!$C$5)) | D33: =AVERAGE(OFFSET('01_Assumptions'!C40,0,0,1,'01_Assumptions'!$C$5)) | E33: =C33-D33 | F33: AVG
B35: OFFSET/INDEX YTD respects the reporting month on Assumptions. LAST KPIs use the as-of month, not a sum.

Sheet 03_Scorecard
B2: Scorecard — actual vs target and RAG
B3: Every value on this sheet is a formula. RAG uses the H / L / R rules and bands on Assumptions.
B4: As-of month | C4: ='01_Assumptions'!D5
B6: As-of month scorecard
B7: KPI | C7: Actual | D7: Target | E7: Var | F7: Var % | G7: RAG | H7: YTD actual | I7: YTD target | J7: YTD var | K7: YTD RAG
B8: ='01_Assumptions'!B14 | C8: =INDEX('02_Actuals'!C7:N7,1,'01_Assumptions'!$C$5) | D8: =INDEX('01_Assumptions'!C29:N29,1,'01_Assumptions'!$C$5) | E8: =C8-D8 | F8: =IF(D8=0,"—",C8/D8-1) | G8: =IF(D8=0,"—",IF('01_Assumptions'!$D$14="H",IF(C8>=D8,"Green",IF(C8>=D8*(1-'01_Assumptions'!$E$14),"Amber","Red")),IF('01_Assumptions'!$D$14="L",IF(C8<=D8,"Green",IF(C8<=D8*(1+'01_Assumptions'!$E$14),"Amber","Red")),IF(ABS(C8/D8-1)<='01_Assumptions'!$F$14,"Green",IF(ABS(C8/D8-1)<='01_Assumptions'!$E$14,"Amber","Red"))))) | H8: ='02_Actuals'!C22 | I8: ='02_Actuals'!D22 | J8: =H8-I8 | K8: =IF(I8=0,"—",IF('01_Assumptions'!$D$14="H",IF(H8>=I8,"Green",IF(H8>=I8*(1-'01_Assumptions'!$E$14),"Amber","Red")),IF('01_Assumptions'!$D$14="L",IF(H8<=I8,"Green",IF(H8<=I8*(1+'01_Assumptions'!$E$14),"Amber","Red")),IF(ABS(H8/I8-1)<='01_Assumptions'!$F$14,"Green",IF(ABS(H8/I8-1)<='01_Assumptions'!$E$14,"Amber","Red")))))
B9: ='01_Assumptions'!B15 | C9: =INDEX('02_Actuals'!C8:N8,1,'01_Assumptions'!$C$5) | D9: =INDEX('01_Assumptions'!C30:N30,1,'01_Assumptions'!$C$5) | E9: =C9-D9 | F9: =IF(D9=0,"—",C9/D9-1) | G9: =IF(D9=0,"—",IF('01_Assumptions'!$D$15="H",IF(C9>=D9,"Green",IF(C9>=D9*(1-'01_Assumptions'!$E$15),"Amber","Red")),IF('01_Assumptions'!$D$15="L",IF(C9<=D9,"Green",IF(C9<=D9*(1+'01_Assumptions'!$E$15),"Amber","Red")),IF(ABS(C9/D9-1)<='01_Assumptions'!$F$15,"Green",IF(ABS(C9/D9-1)<='01_Assumptions'!$E$15,"Amber","Red"))))) | H9: ='02_Actuals'!C23 | I9: ='02_Actuals'!D23 | J9: =H9-I9 | K9: =IF(I9=0,"—",IF('01_Assumptions'!$D$15="H",IF(H9>=I9,"Green",IF(H9>=I9*(1-'01_Assumptions'!$E$15),"Amber","Red")),IF('01_Assumptions'!$D$15="L",IF(H9<=I9,"Green",IF(H9<=I9*(1+'01_Assumptions'!$E$15),"Amber","Red")),IF(ABS(H9/I9-1)<='01_Assumptions'!$F$15,"Green",IF(ABS(H9/I9-1)<='01_Assumptions'!$E$15,"Amber","Red")))))
B10: ='01_Assumptions'!B16 | C10: =INDEX('02_Actuals'!C9:N9,1,'01_Assumptions'!$C$5) | D10: =INDEX('01_Assumptions'!C31:N31,1,'01_Assumptions'!$C$5) | E10: =C10-D10 | F10: =IF(D10=0,"—",C10/D10-1) | G10: =IF(D10=0,"—",IF('01_Assumptions'!$D$16="H",IF(C10>=D10,"Green",IF(C10>=D10*(1-'01_Assumptions'!$E$16),"Amber","Red")),IF('01_Assumptions'!$D$16="L",IF(C10<=D10,"Green",IF(C10<=D10*(1+'01_Assumptions'!$E$16),"Amber","Red")),IF(ABS(C10/D10-1)<='01_Assumptions'!$F$16,"Green",IF(ABS(C10/D10-1)<='01_Assumptions'!$E$16,"Amber","Red"))))) | H10: ='02_Actuals'!C24 | I10: ='02_Actuals'!D24 | J10: =H10-I10 | K10: =IF(I10=0,"—",IF('01_Assumptions'!$D$16="H",IF(H10>=I10,"Green",IF(H10>=I10*(1-'01_Assumptions'!$E$16),"Amber","Red")),IF('01_Assumptions'!$D$16="L",IF(H10<=I10,"Green",IF(H10<=I10*(1+'01_Assumptions'!$E$16),"Amber","Red")),IF(ABS(H10/I10-1)<='01_Assumptions'!$F$16,"Green",IF(ABS(H10/I10-1)<='01_Assumptions'!$E$16,"Amber","Red")))))
B11: ='01_Assumptions'!B17 | C11: =INDEX('02_Actuals'!C10:N10,1,'01_Assumptions'!$C$5) | D11: =INDEX('01_Assumptions'!C32:N32,1,'01_Assumptions'!$C$5) | E11: =C11-D11 | F11: =IF(D11=0,"—",C11/D11-1) | G11: =IF(D11=0,"—",IF('01_Assumptions'!$D$17="H",IF(C11>=D11,"Green",IF(C11>=D11*(1-'01_Assumptions'!$E$17),"Amber","Red")),IF('01_Assumptions'!$D$17="L",IF(C11<=D11,"Green",IF(C11<=D11*(1+'01_Assumptions'!$E$17),"Amber","Red")),IF(ABS(C11/D11-1)<='01_Assumptions'!$F$17,"Green",IF(ABS(C11/D11-1)<='01_Assumptions'!$E$17,"Amber","Red"))))) | H11: ='02_Actuals'!C25 | I11: ='02_Actuals'!D25 | J11: =H11-I11 | K11: =IF(I11=0,"—",IF('01_Assumptions'!$D$17="H",IF(H11>=I11,"Green",IF(H11>=I11*(1-'01_Assumptions'!$E$17),"Amber","Red")),IF('01_Assumptions'!$D$17="L",IF(H11<=I11,"Green",IF(H11<=I11*(1+'01_Assumptions'!$E$17),"Amber","Red")),IF(ABS(H11/I11-1)<='01_Assumptions'!$F$17,"Green",IF(ABS(H11/I11-1)<='01_Assumptions'!$E$17,"Amber","Red")))))
B12: ='01_Assumptions'!B18 | C12: =INDEX('02_Actuals'!C11:N11,1,'01_Assumptions'!$C$5) | D12: =INDEX('01_Assumptions'!C33:N33,1,'01_Assumptions'!$C$5) | E12: =C12-D12 | F12: =IF(D12=0,"—",C12/D12-1) | G12: =IF(D12=0,"—",IF('01_Assumptions'!$D$18="H",IF(C12>=D12,"Green",IF(C12>=D12*(1-'01_Assumptions'!$E$18),"Amber","Red")),IF('01_Assumptions'!$D$18="L",IF(C12<=D12,"Green",IF(C12<=D12*(1+'01_Assumptions'!$E$18),"Amber","Red")),IF(ABS(C12/D12-1)<='01_Assumptions'!$F$18,"Green",IF(ABS(C12/D12-1)<='01_Assumptions'!$E$18,"Amber","Red"))))) | H12: ='02_Actuals'!C26 | I12: ='02_Actuals'!D26 | J12: =H12-I12 | K12: =IF(I12=0,"—",IF('01_Assumptions'!$D$18="H",IF(H12>=I12,"Green",IF(H12>=I12*(1-'01_Assumptions'!$E$18),"Amber","Red")),IF('01_Assumptions'!$D$18="L",IF(H12<=I12,"Green",IF(H12<=I12*(1+'01_Assumptions'!$E$18),"Amber","Red")),IF(ABS(H12/I12-1)<='01_Assumptions'!$F$18,"Green",IF(ABS(H12/I12-1)<='01_Assumptions'!$E$18,"Amber","Red")))))
B13: ='01_Assumptions'!B19 | C13: =INDEX('02_Actuals'!C12:N12,1,'01_Assumptions'!$C$5) | D13: =INDEX('01_Assumptions'!C34:N34,1,'01_Assumptions'!$C$5) | E13: =C13-D13 | F13: =IF(D13=0,"—",C13/D13-1) | G13: =IF(D13=0,"—",IF('01_Assumptions'!$D$19="H",IF(C13>=D13,"Green",IF(C13>=D13*(1-'01_Assumptions'!$E$19),"Amber","Red")),IF('01_Assumptions'!$D$19="L",IF(C13<=D13,"Green",IF(C13<=D13*(1+'01_Assumptions'!$E$19),"Amber","Red")),IF(ABS(C13/D13-1)<='01_Assumptions'!$F$19,"Green",IF(ABS(C13/D13-1)<='01_Assumptions'!$E$19,"Amber","Red"))))) | H13: ='02_Actuals'!C27 | I13: ='02_Actuals'!D27 | J13: =H13-I13 | K13: =IF(I13=0,"—",IF('01_Assumptions'!$D$19="H",IF(H13>=I13,"Green",IF(H13>=I13*(1-'01_Assumptions'!$E$19),"Amber","Red")),IF('01_Assumptions'!$D$19="L",IF(H13<=I13,"Green",IF(H13<=I13*(1+'01_Assumptions'!$E$19),"Amber","Red")),IF(ABS(H13/I13-1)<='01_Assumptions'!$F$19,"Green",IF(ABS(H13/I13-1)<='01_Assumptions'!$E$19,"Amber","Red")))))
B14: ='01_Assumptions'!B20 | C14: =INDEX('02_Actuals'!C13:N13,1,'01_Assumptions'!$C$5) | D14: =INDEX('01_Assumptions'!C35:N35,1,'01_Assumptions'!$C$5) | E14: =C14-D14 | F14: =IF(D14=0,"—",C14/D14-1) | G14: =IF(D14=0,"—",IF('01_Assumptions'!$D$20="H",IF(C14>=D14,"Green",IF(C14>=D14*(1-'01_Assumptions'!$E$20),"Amber","Red")),IF('01_Assumptions'!$D$20="L",IF(C14<=D14,"Green",IF(C14<=D14*(1+'01_Assumptions'!$E$20),"Amber","Red")),IF(ABS(C14/D14-1)<='01_Assumptions'!$F$20,"Green",IF(ABS(C14/D14-1)<='01_Assumptions'!$E$20,"Amber","Red"))))) | H14: ='02_Actuals'!C28 | I14: ='02_Actuals'!D28 | J14: =H14-I14 | K14: =IF(I14=0,"—",IF('01_Assumptions'!$D$20="H",IF(H14>=I14,"Green",IF(H14>=I14*(1-'01_Assumptions'!$E$20),"Amber","Red")),IF('01_Assumptions'!$D$20="L",IF(H14<=I14,"Green",IF(H14<=I14*(1+'01_Assumptions'!$E$20),"Amber","Red")),IF(ABS(H14/I14-1)<='01_Assumptions'!$F$20,"Green",IF(ABS(H14/I14-1)<='01_Assumptions'!$E$20,"Amber","Red")))))
B15: ='01_Assumptions'!B21 | C15: =INDEX('02_Actuals'!C14:N14,1,'01_Assumptions'!$C$5) | D15: =INDEX('01_Assumptions'!C36:N36,1,'01_Assumptions'!$C$5) | E15: =C15-D15 | F15: =IF(D15=0,"—",C15/D15-1) | G15: =IF(D15=0,"—",IF('01_Assumptions'!$D$21="H",IF(C15>=D15,"Green",IF(C15>=D15*(1-'01_Assumptions'!$E$21),"Amber","Red")),IF('01_Assumptions'!$D$21="L",IF(C15<=D15,"Green",IF(C15<=D15*(1+'01_Assumptions'!$E$21),"Amber","Red")),IF(ABS(C15/D15-1)<='01_Assumptions'!$F$21,"Green",IF(ABS(C15/D15-1)<='01_Assumptions'!$E$21,"Amber","Red"))))) | H15: ='02_Actuals'!C29 | I15: ='02_Actuals'!D29 | J15: =H15-I15 | K15: =IF(I15=0,"—",IF('01_Assumptions'!$D$21="H",IF(H15>=I15,"Green",IF(H15>=I15*(1-'01_Assumptions'!$E$21),"Amber","Red")),IF('01_Assumptions'!$D$21="L",IF(H15<=I15,"Green",IF(H15<=I15*(1+'01_Assumptions'!$E$21),"Amber","Red")),IF(ABS(H15/I15-1)<='01_Assumptions'!$F$21,"Green",IF(ABS(H15/I15-1)<='01_Assumptions'!$E$21,"Amber","Red")))))
B16: ='01_Assumptions'!B22 | C16: =INDEX('02_Actuals'!C15:N15,1,'01_Assumptions'!$C$5) | D16: =INDEX('01_Assumptions'!C37:N37,1,'01_Assumptions'!$C$5) | E16: =C16-D16 | F16: =IF(D16=0,"—",C16/D16-1) | G16: =IF(D16=0,"—",IF('01_Assumptions'!$D$22="H",IF(C16>=D16,"Green",IF(C16>=D16*(1-'01_Assumptions'!$E$22),"Amber","Red")),IF('01_Assumptions'!$D$22="L",IF(C16<=D16,"Green",IF(C16<=D16*(1+'01_Assumptions'!$E$22),"Amber","Red")),IF(ABS(C16/D16-1)<='01_Assumptions'!$F$22,"Green",IF(ABS(C16/D16-1)<='01_Assumptions'!$E$22,"Amber","Red"))))) | H16: ='02_Actuals'!C30 | I16: ='02_Actuals'!D30 | J16: =H16-I16 | K16: =IF(I16=0,"—",IF('01_Assumptions'!$D$22="H",IF(H16>=I16,"Green",IF(H16>=I16*(1-'01_Assumptions'!$E$22),"Amber","Red")),IF('01_Assumptions'!$D$22="L",IF(H16<=I16,"Green",IF(H16<=I16*(1+'01_Assumptions'!$E$22),"Amber","Red")),IF(ABS(H16/I16-1)<='01_Assumptions'!$F$22,"Green",IF(ABS(H16/I16-1)<='01_Assumptions'!$E$22,"Amber","Red")))))
B17: ='01_Assumptions'!B23 | C17: =INDEX('02_Actuals'!C16:N16,1,'01_Assumptions'!$C$5) | D17: =INDEX('01_Assumptions'!C38:N38,1,'01_Assumptions'!$C$5) | E17: =C17-D17 | F17: =IF(D17=0,"—",C17/D17-1) | G17: =IF(D17=0,"—",IF('01_Assumptions'!$D$23="H",IF(C17>=D17,"Green",IF(C17>=D17*(1-'01_Assumptions'!$E$23),"Amber","Red")),IF('01_Assumptions'!$D$23="L",IF(C17<=D17,"Green",IF(C17<=D17*(1+'01_Assumptions'!$E$23),"Amber","Red")),IF(ABS(C17/D17-1)<='01_Assumptions'!$F$23,"Green",IF(ABS(C17/D17-1)<='01_Assumptions'!$E$23,"Amber","Red"))))) | H17: ='02_Actuals'!C31 | I17: ='02_Actuals'!D31 | J17: =H17-I17 | K17: =IF(I17=0,"—",IF('01_Assumptions'!$D$23="H",IF(H17>=I17,"Green",IF(H17>=I17*(1-'01_Assumptions'!$E$23),"Amber","Red")),IF('01_Assumptions'!$D$23="L",IF(H17<=I17,"Green",IF(H17<=I17*(1+'01_Assumptions'!$E$23),"Amber","Red")),IF(ABS(H17/I17-1)<='01_Assumptions'!$F$23,"Green",IF(ABS(H17/I17-1)<='01_Assumptions'!$E$23,"Amber","Red")))))
B18: ='01_Assumptions'!B24 | C18: =INDEX('02_Actuals'!C17:N17,1,'01_Assumptions'!$C$5) | D18: =INDEX('01_Assumptions'!C39:N39,1,'01_Assumptions'!$C$5) | E18: =C18-D18 | F18: =IF(D18=0,"—",C18/D18-1) | G18: =IF(D18=0,"—",IF('01_Assumptions'!$D$24="H",IF(C18>=D18,"Green",IF(C18>=D18*(1-'01_Assumptions'!$E$24),"Amber","Red")),IF('01_Assumptions'!$D$24="L",IF(C18<=D18,"Green",IF(C18<=D18*(1+'01_Assumptions'!$E$24),"Amber","Red")),IF(ABS(C18/D18-1)<='01_Assumptions'!$F$24,"Green",IF(ABS(C18/D18-1)<='01_Assumptions'!$E$24,"Amber","Red"))))) | H18: ='02_Actuals'!C32 | I18: ='02_Actuals'!D32 | J18: =H18-I18 | K18: =IF(I18=0,"—",IF('01_Assumptions'!$D$24="H",IF(H18>=I18,"Green",IF(H18>=I18*(1-'01_Assumptions'!$E$24),"Amber","Red")),IF('01_Assumptions'!$D$24="L",IF(H18<=I18,"Green",IF(H18<=I18*(1+'01_Assumptions'!$E$24),"Amber","Red")),IF(ABS(H18/I18-1)<='01_Assumptions'!$F$24,"Green",IF(ABS(H18/I18-1)<='01_Assumptions'!$E$24,"Amber","Red")))))
B19: ='01_Assumptions'!B25 | C19: =INDEX('02_Actuals'!C18:N18,1,'01_Assumptions'!$C$5) | D19: =INDEX('01_Assumptions'!C40:N40,1,'01_Assumptions'!$C$5) | E19: =C19-D19 | F19: =IF(D19=0,"—",C19/D19-1) | G19: =IF(D19=0,"—",IF('01_Assumptions'!$D$25="H",IF(C19>=D19,"Green",IF(C19>=D19*(1-'01_Assumptions'!$E$25),"Amber","Red")),IF('01_Assumptions'!$D$25="L",IF(C19<=D19,"Green",IF(C19<=D19*(1+'01_Assumptions'!$E$25),"Amber","Red")),IF(ABS(C19/D19-1)<='01_Assumptions'!$F$25,"Green",IF(ABS(C19/D19-1)<='01_Assumptions'!$E$25,"Amber","Red"))))) | H19: ='02_Actuals'!C33 | I19: ='02_Actuals'!D33 | J19: =H19-I19 | K19: =IF(I19=0,"—",IF('01_Assumptions'!$D$25="H",IF(H19>=I19,"Green",IF(H19>=I19*(1-'01_Assumptions'!$E$25),"Amber","Red")),IF('01_Assumptions'!$D$25="L",IF(H19<=I19,"Green",IF(H19<=I19*(1+'01_Assumptions'!$E$25),"Amber","Red")),IF(ABS(H19/I19-1)<='01_Assumptions'!$F$25,"Green",IF(ABS(H19/I19-1)<='01_Assumptions'!$E$25,"Amber","Red")))))
B21: Monthly RAG heatmap
C22: Jan-26 | D22: Feb-26 | E22: Mar-26 | F22: Apr-26 | G22: May-26 | H22: Jun-26 | I22: Jul-26 | J22: Aug-26 | K22: Sep-26 | L22: Oct-26 | M22: Nov-26 | N22: Dec-26
B23: Net revenue | C23: =IF('01_Assumptions'!C29=0,"—",IF('01_Assumptions'!$D$14="H",IF('02_Actuals'!C7>='01_Assumptions'!C29,"Green",IF('02_Actuals'!C7>='01_Assumptions'!C29*(1-'01_Assumptions'!$E$14),"Amber","Red")),IF('01_Assumptions'!$D$14="L",IF('02_Actuals'!C7<='01_Assumptions'!C29,"Green",IF('02_Actuals'!C7<='01_Assumptions'!C29*(1+'01_Assumptions'!$E$14),"Amber","Red")),IF(ABS('02_Actuals'!C7/'01_Assumptions'!C29-1)<='01_Assumptions'!$F$14,"Green",IF(ABS('02_Actuals'!C7/'01_Assumptions'!C29-1)<='01_Assumptions'!$E$14,"Amber","Red"))))) | D23: =IF('01_Assumptions'!D29=0,"—",IF('01_Assumptions'!$D$14="H",IF('02_Actuals'!D7>='01_Assumptions'!D29,"Green",IF('02_Actuals'!D7>='01_Assumptions'!D29*(1-'01_Assumptions'!$E$14),"Amber","Red")),IF('01_Assumptions'!$D$14="L",IF('02_Actuals'!D7<='01_Assumptions'!D29,"Green",IF('02_Actuals'!D7<='01_Assumptions'!D29*(1+'01_Assumptions'!$E$14),"Amber","Red")),IF(ABS('02_Actuals'!D7/'01_Assumptions'!D29-1)<='01_Assumptions'!$F$14,"Green",IF(ABS('02_Actuals'!D7/'01_Assumptions'!D29-1)<='01_Assumptions'!$E$14,"Amber","Red"))))) | E23: =IF('01_Assumptions'!E29=0,"—",IF('01_Assumptions'!$D$14="H",IF('02_Actuals'!E7>='01_Assumptions'!E29,"Green",IF('02_Actuals'!E7>='01_Assumptions'!E29*(1-'01_Assumptions'!$E$14),"Amber","Red")),IF('01_Assumptions'!$D$14="L",IF('02_Actuals'!E7<='01_Assumptions'!E29,"Green",IF('02_Actuals'!E7<='01_Assumptions'!E29*(1+'01_Assumptions'!$E$14),"Amber","Red")),IF(ABS('02_Actuals'!E7/'01_Assumptions'!E29-1)<='01_Assumptions'!$F$14,"Green",IF(ABS('02_Actuals'!E7/'01_Assumptions'!E29-1)<='01_Assumptions'!$E$14,"Amber","Red"))))) | F23: =IF('01_Assumptions'!F29=0,"—",IF('01_Assumptions'!$D$14="H",IF('02_Actuals'!F7>='01_Assumptions'!F29,"Green",IF('02_Actuals'!F7>='01_Assumptions'!F29*(1-'01_Assumptions'!$E$14),"Amber","Red")),IF('01_Assumptions'!$D$14="L",IF('02_Actuals'!F7<='01_Assumptions'!F29,"Green",IF('02_Actuals'!F7<='01_Assumptions'!F29*(1+'01_Assumptions'!$E$14),"Amber","Red")),IF(ABS('02_Actuals'!F7/'01_Assumptions'!F29-1)<='01_Assumptions'!$F$14,"Green",IF(ABS('02_Actuals'!F7/'01_Assumptions'!F29-1)<='01_Assumptions'!$E$14,"Amber","Red"))))) | G23: =IF('01_Assumptions'!G29=0,"—",IF('01_Assumptions'!$D$14="H",IF('02_Actuals'!G7>='01_Assumptions'!G29,"Green",IF('02_Actuals'!G7>='01_Assumptions'!G29*(1-'01_Assumptions'!$E$14),"Amber","Red")),IF('01_Assumptions'!$D$14="L",IF('02_Actuals'!G7<='01_Assumptions'!G29,"Green",IF('02_Actuals'!G7<='01_Assumptions'!G29*(1+'01_Assumptions'!$E$14),"Amber","Red")),IF(ABS('02_Actuals'!G7/'01_Assumptions'!G29-1)<='01_Assumptions'!$F$14,"Green",IF(ABS('02_Actuals'!G7/'01_Assumptions'!G29-1)<='01_Assumptions'!$E$14,"Amber","Red"))))) | H23: =IF('01_Assumptions'!H29=0,"—",IF('01_Assumptions'!$D$14="H",IF('02_Actuals'!H7>='01_Assumptions'!H29,"Green",IF('02_Actuals'!H7>='01_Assumptions'!H29*(1-'01_Assumptions'!$E$14),"Amber","Red")),IF('01_Assumptions'!$D$14="L",IF('02_Actuals'!H7<='01_Assumptions'!H29,"Green",IF('02_Actuals'!H7<='01_Assumptions'!H29*(1+'01_Assumptions'!$E$14),"Amber","Red")),IF(ABS('02_Actuals'!H7/'01_Assumptions'!H29-1)<='01_Assumptions'!$F$14,"Green",IF(ABS('02_Actuals'!H7/'01_Assumptions'!H29-1)<='01_Assumptions'!$E$14,"Amber","Red"))))) | I23: =IF('01_Assumptions'!I29=0,"—",IF('01_Assumptions'!$D$14="H",IF('02_Actuals'!I7>='01_Assumptions'!I29,"Green",IF('02_Actuals'!I7>='01_Assumptions'!I29*(1-'01_Assumptions'!$E$14),"Amber","Red")),IF('01_Assumptions'!$D$14="L",IF('02_Actuals'!I7<='01_Assumptions'!I29,"Green",IF('02_Actuals'!I7<='01_Assumptions'!I29*(1+'01_Assumptions'!$E$14),"Amber","Red")),IF(ABS('02_Actuals'!I7/'01_Assumptions'!I29-1)<='01_Assumptions'!$F$14,"Green",IF(ABS('02_Actuals'!I7/'01_Assumptions'!I29-1)<='01_Assumptions'!$E$14,"Amber","Red"))))) | J23: =IF('01_Assumptions'!J29=0,"—",IF('01_Assumptions'!$D$14="H",IF('02_Actuals'!J7>='01_Assumptions'!J29,"Green",IF('02_Actuals'!J7>='01_Assumptions'!J29*(1-'01_Assumptions'!$E$14),"Amber","Red")),IF('01_Assumptions'!$D$14="L",IF('02_Actuals'!J7<='01_Assumptions'!J29,"Green",IF('02_Actuals'!J7<='01_Assumptions'!J29*(1+'01_Assumptions'!$E$14),"Amber","Red")),IF(ABS('02_Actuals'!J7/'01_Assumptions'!J29-1)<='01_Assumptions'!$F$14,"Green",IF(ABS('02_Actuals'!J7/'01_Assumptions'!J29-1)<='01_Assumptions'!$E$14,"Amber","Red"))))) | ... N23: =IF('01_Assumptions'!N29=0,"—",IF('01_Assumptions'!$D$14="H",IF('02_Actuals'!N7>='01_Assumptions'!N29,"Green",IF('02_Actuals'!N7>='01_Assumptions'!N29*(1-'01_Assumptions'!$E$14),"Amber","Red")),IF('01_Assumptions'!$D$14="L",IF('02_Actuals'!N7<='01_Assumptions'!N29,"Green",IF('02_Actuals'!N7<='01_Assumptions'!N29*(1+'01_Assumptions'!$E$14),"Amber","Red")),IF(ABS('02_Actuals'!N7/'01_Assumptions'!N29-1)<='01_Assumptions'!$F$14,"Green",IF(ABS('02_Actuals'!N7/'01_Assumptions'!N29-1)<='01_Assumptions'!$E$14,"Amber","Red")))))
B24: Gross margin % | C24: =IF('01_Assumptions'!C30=0,"—",IF('01_Assumptions'!$D$15="H",IF('02_Actuals'!C8>='01_Assumptions'!C30,"Green",IF('02_Actuals'!C8>='01_Assumptions'!C30*(1-'01_Assumptions'!$E$15),"Amber","Red")),IF('01_Assumptions'!$D$15="L",IF('02_Actuals'!C8<='01_Assumptions'!C30,"Green",IF('02_Actuals'!C8<='01_Assumptions'!C30*(1+'01_Assumptions'!$E$15),"Amber","Red")),IF(ABS('02_Actuals'!C8/'01_Assumptions'!C30-1)<='01_Assumptions'!$F$15,"Green",IF(ABS('02_Actuals'!C8/'01_Assumptions'!C30-1)<='01_Assumptions'!$E$15,"Amber","Red"))))) | D24: =IF('01_Assumptions'!D30=0,"—",IF('01_Assumptions'!$D$15="H",IF('02_Actuals'!D8>='01_Assumptions'!D30,"Green",IF('02_Actuals'!D8>='01_Assumptions'!D30*(1-'01_Assumptions'!$E$15),"Amber","Red")),IF('01_Assumptions'!$D$15="L",IF('02_Actuals'!D8<='01_Assumptions'!D30,"Green",IF('02_Actuals'!D8<='01_Assumptions'!D30*(1+'01_Assumptions'!$E$15),"Amber","Red")),IF(ABS('02_Actuals'!D8/'01_Assumptions'!D30-1)<='01_Assumptions'!$F$15,"Green",IF(ABS('02_Actuals'!D8/'01_Assumptions'!D30-1)<='01_Assumptions'!$E$15,"Amber","Red"))))) | E24: =IF('01_Assumptions'!E30=0,"—",IF('01_Assumptions'!$D$15="H",IF('02_Actuals'!E8>='01_Assumptions'!E30,"Green",IF('02_Actuals'!E8>='01_Assumptions'!E30*(1-'01_Assumptions'!$E$15),"Amber","Red")),IF('01_Assumptions'!$D$15="L",IF('02_Actuals'!E8<='01_Assumptions'!E30,"Green",IF('02_Actuals'!E8<='01_Assumptions'!E30*(1+'01_Assumptions'!$E$15),"Amber","Red")),IF(ABS('02_Actuals'!E8/'01_Assumptions'!E30-1)<='01_Assumptions'!$F$15,"Green",IF(ABS('02_Actuals'!E8/'01_Assumptions'!E30-1)<='01_Assumptions'!$E$15,"Amber","Red"))))) | F24: =IF('01_Assumptions'!F30=0,"—",IF('01_Assumptions'!$D$15="H",IF('02_Actuals'!F8>='01_Assumptions'!F30,"Green",IF('02_Actuals'!F8>='01_Assumptions'!F30*(1-'01_Assumptions'!$E$15),"Amber","Red")),IF('01_Assumptions'!$D$15="L",IF('02_Actuals'!F8<='01_Assumptions'!F30,"Green",IF('02_Actuals'!F8<='01_Assumptions'!F30*(1+'01_Assumptions'!$E$15),"Amber","Red")),IF(ABS('02_Actuals'!F8/'01_Assumptions'!F30-1)<='01_Assumptions'!$F$15,"Green",IF(ABS('02_Actuals'!F8/'01_Assumptions'!F30-1)<='01_Assumptions'!$E$15,"Amber","Red"))))) | G24: =IF('01_Assumptions'!G30=0,"—",IF('01_Assumptions'!$D$15="H",IF('02_Actuals'!G8>='01_Assumptions'!G30,"Green",IF('02_Actuals'!G8>='01_Assumptions'!G30*(1-'01_Assumptions'!$E$15),"Amber","Red")),IF('01_Assumptions'!$D$15="L",IF('02_Actuals'!G8<='01_Assumptions'!G30,"Green",IF('02_Actuals'!G8<='01_Assumptions'!G30*(1+'01_Assumptions'!$E$15),"Amber","Red")),IF(ABS('02_Actuals'!G8/'01_Assumptions'!G30-1)<='01_Assumptions'!$F$15,"Green",IF(ABS('02_Actuals'!G8/'01_Assumptions'!G30-1)<='01_Assumptions'!$E$15,"Amber","Red"))))) | H24: =IF('01_Assumptions'!H30=0,"—",IF('01_Assumptions'!$D$15="H",IF('02_Actuals'!H8>='01_Assumptions'!H30,"Green",IF('02_Actuals'!H8>='01_Assumptions'!H30*(1-'01_Assumptions'!$E$15),"Amber","Red")),IF('01_Assumptions'!$D$15="L",IF('02_Actuals'!H8<='01_Assumptions'!H30,"Green",IF('02_Actuals'!H8<='01_Assumptions'!H30*(1+'01_Assumptions'!$E$15),"Amber","Red")),IF(ABS('02_Actuals'!H8/'01_Assumptions'!H30-1)<='01_Assumptions'!$F$15,"Green",IF(ABS('02_Actuals'!H8/'01_Assumptions'!H30-1)<='01_Assumptions'!$E$15,"Amber","Red"))))) | I24: =IF('01_Assumptions'!I30=0,"—",IF('01_Assumptions'!$D$15="H",IF('02_Actuals'!I8>='01_Assumptions'!I30,"Green",IF('02_Actuals'!I8>='01_Assumptions'!I30*(1-'01_Assumptions'!$E$15),"Amber","Red")),IF('01_Assumptions'!$D$15="L",IF('02_Actuals'!I8<='01_Assumptions'!I30,"Green",IF('02_Actuals'!I8<='01_Assumptions'!I30*(1+'01_Assumptions'!$E$15),"Amber","Red")),IF(ABS('02_Actuals'!I8/'01_Assumptions'!I30-1)<='01_Assumptions'!$F$15,"Green",IF(ABS('02_Actuals'!I8/'01_Assumptions'!I30-1)<='01_Assumptions'!$E$15,"Amber","Red"))))) | J24: =IF('01_Assumptions'!J30=0,"—",IF('01_Assumptions'!$D$15="H",IF('02_Actuals'!J8>='01_Assumptions'!J30,"Green",IF('02_Actuals'!J8>='01_Assumptions'!J30*(1-'01_Assumptions'!$E$15),"Amber","Red")),IF('01_Assumptions'!$D$15="L",IF('02_Actuals'!J8<='01_Assumptions'!J30,"Green",IF('02_Actuals'!J8<='01_Assumptions'!J30*(1+'01_Assumptions'!$E$15),"Amber","Red")),IF(ABS('02_Actuals'!J8/'01_Assumptions'!J30-1)<='01_Assumptions'!$F$15,"Green",IF(ABS('02_Actuals'!J8/'01_Assumptions'!J30-1)<='01_Assumptions'!$E$15,"Amber","Red"))))) | ... N24: =IF('01_Assumptions'!N30=0,"—",IF('01_Assumptions'!$D$15="H",IF('02_Actuals'!N8>='01_Assumptions'!N30,"Green",IF('02_Actuals'!N8>='01_Assumptions'!N30*(1-'01_Assumptions'!$E$15),"Amber","Red")),IF('01_Assumptions'!$D$15="L",IF('02_Actuals'!N8<='01_Assumptions'!N30,"Green",IF('02_Actuals'!N8<='01_Assumptions'!N30*(1+'01_Assumptions'!$E$15),"Amber","Red")),IF(ABS('02_Actuals'!N8/'01_Assumptions'!N30-1)<='01_Assumptions'!$F$15,"Green",IF(ABS('02_Actuals'!N8/'01_Assumptions'!N30-1)<='01_Assumptions'!$E$15,"Amber","Red")))))
B25: EBITDA | C25: =IF('01_Assumptions'!C31=0,"—",IF('01_Assumptions'!$D$16="H",IF('02_Actuals'!C9>='01_Assumptions'!C31,"Green",IF('02_Actuals'!C9>='01_Assumptions'!C31*(1-'01_Assumptions'!$E$16),"Amber","Red")),IF('01_Assumptions'!$D$16="L",IF('02_Actuals'!C9<='01_Assumptions'!C31,"Green",IF('02_Actuals'!C9<='01_Assumptions'!C31*(1+'01_Assumptions'!$E$16),"Amber","Red")),IF(ABS('02_Actuals'!C9/'01_Assumptions'!C31-1)<='01_Assumptions'!$F$16,"Green",IF(ABS('02_Actuals'!C9/'01_Assumptions'!C31-1)<='01_Assumptions'!$E$16,"Amber","Red"))))) | D25: =IF('01_Assumptions'!D31=0,"—",IF('01_Assumptions'!$D$16="H",IF('02_Actuals'!D9>='01_Assumptions'!D31,"Green",IF('02_Actuals'!D9>='01_Assumptions'!D31*(1-'01_Assumptions'!$E$16),"Amber","Red")),IF('01_Assumptions'!$D$16="L",IF('02_Actuals'!D9<='01_Assumptions'!D31,"Green",IF('02_Actuals'!D9<='01_Assumptions'!D31*(1+'01_Assumptions'!$E$16),"Amber","Red")),IF(ABS('02_Actuals'!D9/'01_Assumptions'!D31-1)<='01_Assumptions'!$F$16,"Green",IF(ABS('02_Actuals'!D9/'01_Assumptions'!D31-1)<='01_Assumptions'!$E$16,"Amber","Red"))))) | E25: =IF('01_Assumptions'!E31=0,"—",IF('01_Assumptions'!$D$16="H",IF('02_Actuals'!E9>='01_Assumptions'!E31,"Green",IF('02_Actuals'!E9>='01_Assumptions'!E31*(1-'01_Assumptions'!$E$16),"Amber","Red")),IF('01_Assumptions'!$D$16="L",IF('02_Actuals'!E9<='01_Assumptions'!E31,"Green",IF('02_Actuals'!E9<='01_Assumptions'!E31*(1+'01_Assumptions'!$E$16),"Amber","Red")),IF(ABS('02_Actuals'!E9/'01_Assumptions'!E31-1)<='01_Assumptions'!$F$16,"Green",IF(ABS('02_Actuals'!E9/'01_Assumptions'!E31-1)<='01_Assumptions'!$E$16,"Amber","Red"))))) | F25: =IF('01_Assumptions'!F31=0,"—",IF('01_Assumptions'!$D$16="H",IF('02_Actuals'!F9>='01_Assumptions'!F31,"Green",IF('02_Actuals'!F9>='01_Assumptions'!F31*(1-'01_Assumptions'!$E$16),"Amber","Red")),IF('01_Assumptions'!$D$16="L",IF('02_Actuals'!F9<='01_Assumptions'!F31,"Green",IF('02_Actuals'!F9<='01_Assumptions'!F31*(1+'01_Assumptions'!$E$16),"Amber","Red")),IF(ABS('02_Actuals'!F9/'01_Assumptions'!F31-1)<='01_Assumptions'!$F$16,"Green",IF(ABS('02_Actuals'!F9/'01_Assumptions'!F31-1)<='01_Assumptions'!$E$16,"Amber","Red"))))) | G25: =IF('01_Assumptions'!G31=0,"—",IF('01_Assumptions'!$D$16="H",IF('02_Actuals'!G9>='01_Assumptions'!G31,"Green",IF('02_Actuals'!G9>='01_Assumptions'!G31*(1-'01_Assumptions'!$E$16),"Amber","Red")),IF('01_Assumptions'!$D$16="L",IF('02_Actuals'!G9<='01_Assumptions'!G31,"Green",IF('02_Actuals'!G9<='01_Assumptions'!G31*(1+'01_Assumptions'!$E$16),"Amber","Red")),IF(ABS('02_Actuals'!G9/'01_Assumptions'!G31-1)<='01_Assumptions'!$F$16,"Green",IF(ABS('02_Actuals'!G9/'01_Assumptions'!G31-1)<='01_Assumptions'!$E$16,"Amber","Red"))))) | H25: =IF('01_Assumptions'!H31=0,"—",IF('01_Assumptions'!$D$16="H",IF('02_Actuals'!H9>='01_Assumptions'!H31,"Green",IF('02_Actuals'!H9>='01_Assumptions'!H31*(1-'01_Assumptions'!$E$16),"Amber","Red")),IF('01_Assumptions'!$D$16="L",IF('02_Actuals'!H9<='01_Assumptions'!H31,"Green",IF('02_Actuals'!H9<='01_Assumptions'!H31*(1+'01_Assumptions'!$E$16),"Amber","Red")),IF(ABS('02_Actuals'!H9/'01_Assumptions'!H31-1)<='01_Assumptions'!$F$16,"Green",IF(ABS('02_Actuals'!H9/'01_Assumptions'!H31-1)<='01_Assumptions'!$E$16,"Amber","Red"))))) | I25: =IF('01_Assumptions'!I31=0,"—",IF('01_Assumptions'!$D$16="H",IF('02_Actuals'!I9>='01_Assumptions'!I31,"Green",IF('02_Actuals'!I9>='01_Assumptions'!I31*(1-'01_Assumptions'!$E$16),"Amber","Red")),IF('01_Assumptions'!$D$16="L",IF('02_Actuals'!I9<='01_Assumptions'!I31,"Green",IF('02_Actuals'!I9<='01_Assumptions'!I31*(1+'01_Assumptions'!$E$16),"Amber","Red")),IF(ABS('02_Actuals'!I9/'01_Assumptions'!I31-1)<='01_Assumptions'!$F$16,"Green",IF(ABS('02_Actuals'!I9/'01_Assumptions'!I31-1)<='01_Assumptions'!$E$16,"Amber","Red"))))) | J25: =IF('01_Assumptions'!J31=0,"—",IF('01_Assumptions'!$D$16="H",IF('02_Actuals'!J9>='01_Assumptions'!J31,"Green",IF('02_Actuals'!J9>='01_Assumptions'!J31*(1-'01_Assumptions'!$E$16),"Amber","Red")),IF('01_Assumptions'!$D$16="L",IF('02_Actuals'!J9<='01_Assumptions'!J31,"Green",IF('02_Actuals'!J9<='01_Assumptions'!J31*(1+'01_Assumptions'!$E$16),"Amber","Red")),IF(ABS('02_Actuals'!J9/'01_Assumptions'!J31-1)<='01_Assumptions'!$F$16,"Green",IF(ABS('02_Actuals'!J9/'01_Assumptions'!J31-1)<='01_Assumptions'!$E$16,"Amber","Red"))))) | ... N25: =IF('01_Assumptions'!N31=0,"—",IF('01_Assumptions'!$D$16="H",IF('02_Actuals'!N9>='01_Assumptions'!N31,"Green",IF('02_Actuals'!N9>='01_Assumptions'!N31*(1-'01_Assumptions'!$E$16),"Amber","Red")),IF('01_Assumptions'!$D$16="L",IF('02_Actuals'!N9<='01_Assumptions'!N31,"Green",IF('02_Actuals'!N9<='01_Assumptions'!N31*(1+'01_Assumptions'!$E$16),"Amber","Red")),IF(ABS('02_Actuals'!N9/'01_Assumptions'!N31-1)<='01_Assumptions'!$F$16,"Green",IF(ABS('02_Actuals'!N9/'01_Assumptions'!N31-1)<='01_Assumptions'!$E$16,"Amber","Red")))))
B26: Volume | C26: =IF('01_Assumptions'!C32=0,"—",IF('01_Assumptions'!$D$17="H",IF('02_Actuals'!C10>='01_Assumptions'!C32,"Green",IF('02_Actuals'!C10>='01_Assumptions'!C32*(1-'01_Assumptions'!$E$17),"Amber","Red")),IF('01_Assumptions'!$D$17="L",IF('02_Actuals'!C10<='01_Assumptions'!C32,"Green",IF('02_Actuals'!C10<='01_Assumptions'!C32*(1+'01_Assumptions'!$E$17),"Amber","Red")),IF(ABS('02_Actuals'!C10/'01_Assumptions'!C32-1)<='01_Assumptions'!$F$17,"Green",IF(ABS('02_Actuals'!C10/'01_Assumptions'!C32-1)<='01_Assumptions'!$E$17,"Amber","Red"))))) | D26: =IF('01_Assumptions'!D32=0,"—",IF('01_Assumptions'!$D$17="H",IF('02_Actuals'!D10>='01_Assumptions'!D32,"Green",IF('02_Actuals'!D10>='01_Assumptions'!D32*(1-'01_Assumptions'!$E$17),"Amber","Red")),IF('01_Assumptions'!$D$17="L",IF('02_Actuals'!D10<='01_Assumptions'!D32,"Green",IF('02_Actuals'!D10<='01_Assumptions'!D32*(1+'01_Assumptions'!$E$17),"Amber","Red")),IF(ABS('02_Actuals'!D10/'01_Assumptions'!D32-1)<='01_Assumptions'!$F$17,"Green",IF(ABS('02_Actuals'!D10/'01_Assumptions'!D32-1)<='01_Assumptions'!$E$17,"Amber","Red"))))) | E26: =IF('01_Assumptions'!E32=0,"—",IF('01_Assumptions'!$D$17="H",IF('02_Actuals'!E10>='01_Assumptions'!E32,"Green",IF('02_Actuals'!E10>='01_Assumptions'!E32*(1-'01_Assumptions'!$E$17),"Amber","Red")),IF('01_Assumptions'!$D$17="L",IF('02_Actuals'!E10<='01_Assumptions'!E32,"Green",IF('02_Actuals'!E10<='01_Assumptions'!E32*(1+'01_Assumptions'!$E$17),"Amber","Red")),IF(ABS('02_Actuals'!E10/'01_Assumptions'!E32-1)<='01_Assumptions'!$F$17,"Green",IF(ABS('02_Actuals'!E10/'01_Assumptions'!E32-1)<='01_Assumptions'!$E$17,"Amber","Red"))))) | F26: =IF('01_Assumptions'!F32=0,"—",IF('01_Assumptions'!$D$17="H",IF('02_Actuals'!F10>='01_Assumptions'!F32,"Green",IF('02_Actuals'!F10>='01_Assumptions'!F32*(1-'01_Assumptions'!$E$17),"Amber","Red")),IF('01_Assumptions'!$D$17="L",IF('02_Actuals'!F10<='01_Assumptions'!F32,"Green",IF('02_Actuals'!F10<='01_Assumptions'!F32*(1+'01_Assumptions'!$E$17),"Amber","Red")),IF(ABS('02_Actuals'!F10/'01_Assumptions'!F32-1)<='01_Assumptions'!$F$17,"Green",IF(ABS('02_Actuals'!F10/'01_Assumptions'!F32-1)<='01_Assumptions'!$E$17,"Amber","Red"))))) | G26: =IF('01_Assumptions'!G32=0,"—",IF('01_Assumptions'!$D$17="H",IF('02_Actuals'!G10>='01_Assumptions'!G32,"Green",IF('02_Actuals'!G10>='01_Assumptions'!G32*(1-'01_Assumptions'!$E$17),"Amber","Red")),IF('01_Assumptions'!$D$17="L",IF('02_Actuals'!G10<='01_Assumptions'!G32,"Green",IF('02_Actuals'!G10<='01_Assumptions'!G32*(1+'01_Assumptions'!$E$17),"Amber","Red")),IF(ABS('02_Actuals'!G10/'01_Assumptions'!G32-1)<='01_Assumptions'!$F$17,"Green",IF(ABS('02_Actuals'!G10/'01_Assumptions'!G32-1)<='01_Assumptions'!$E$17,"Amber","Red"))))) | H26: =IF('01_Assumptions'!H32=0,"—",IF('01_Assumptions'!$D$17="H",IF('02_Actuals'!H10>='01_Assumptions'!H32,"Green",IF('02_Actuals'!H10>='01_Assumptions'!H32*(1-'01_Assumptions'!$E$17),"Amber","Red")),IF('01_Assumptions'!$D$17="L",IF('02_Actuals'!H10<='01_Assumptions'!H32,"Green",IF('02_Actuals'!H10<='01_Assumptions'!H32*(1+'01_Assumptions'!$E$17),"Amber","Red")),IF(ABS('02_Actuals'!H10/'01_Assumptions'!H32-1)<='01_Assumptions'!$F$17,"Green",IF(ABS('02_Actuals'!H10/'01_Assumptions'!H32-1)<='01_Assumptions'!$E$17,"Amber","Red"))))) | I26: =IF('01_Assumptions'!I32=0,"—",IF('01_Assumptions'!$D$17="H",IF('02_Actuals'!I10>='01_Assumptions'!I32,"Green",IF('02_Actuals'!I10>='01_Assumptions'!I32*(1-'01_Assumptions'!$E$17),"Amber","Red")),IF('01_Assumptions'!$D$17="L",IF('02_Actuals'!I10<='01_Assumptions'!I32,"Green",IF('02_Actuals'!I10<='01_Assumptions'!I32*(1+'01_Assumptions'!$E$17),"Amber","Red")),IF(ABS('02_Actuals'!I10/'01_Assumptions'!I32-1)<='01_Assumptions'!$F$17,"Green",IF(ABS('02_Actuals'!I10/'01_Assumptions'!I32-1)<='01_Assumptions'!$E$17,"Amber","Red"))))) | J26: =IF('01_Assumptions'!J32=0,"—",IF('01_Assumptions'!$D$17="H",IF('02_Actuals'!J10>='01_Assumptions'!J32,"Green",IF('02_Actuals'!J10>='01_Assumptions'!J32*(1-'01_Assumptions'!$E$17),"Amber","Red")),IF('01_Assumptions'!$D$17="L",IF('02_Actuals'!J10<='01_Assumptions'!J32,"Green",IF('02_Actuals'!J10<='01_Assumptions'!J32*(1+'01_Assumptions'!$E$17),"Amber","Red")),IF(ABS('02_Actuals'!J10/'01_Assumptions'!J32-1)<='01_Assumptions'!$F$17,"Green",IF(ABS('02_Actuals'!J10/'01_Assumptions'!J32-1)<='01_Assumptions'!$E$17,"Amber","Red"))))) | ... N26: =IF('01_Assumptions'!N32=0,"—",IF('01_Assumptions'!$D$17="H",IF('02_Actuals'!N10>='01_Assumptions'!N32,"Green",IF('02_Actuals'!N10>='01_Assumptions'!N32*(1-'01_Assumptions'!$E$17),"Amber","Red")),IF('01_Assumptions'!$D$17="L",IF('02_Actuals'!N10<='01_Assumptions'!N32,"Green",IF('02_Actuals'!N10<='01_Assumptions'!N32*(1+'01_Assumptions'!$E$17),"Amber","Red")),IF(ABS('02_Actuals'!N10/'01_Assumptions'!N32-1)<='01_Assumptions'!$F$17,"Green",IF(ABS('02_Actuals'!N10/'01_Assumptions'!N32-1)<='01_Assumptions'!$E$17,"Amber","Red")))))
B27: OTIF % | C27: =IF('01_Assumptions'!C33=0,"—",IF('01_Assumptions'!$D$18="H",IF('02_Actuals'!C11>='01_Assumptions'!C33,"Green",IF('02_Actuals'!C11>='01_Assumptions'!C33*(1-'01_Assumptions'!$E$18),"Amber","Red")),IF('01_Assumptions'!$D$18="L",IF('02_Actuals'!C11<='01_Assumptions'!C33,"Green",IF('02_Actuals'!C11<='01_Assumptions'!C33*(1+'01_Assumptions'!$E$18),"Amber","Red")),IF(ABS('02_Actuals'!C11/'01_Assumptions'!C33-1)<='01_Assumptions'!$F$18,"Green",IF(ABS('02_Actuals'!C11/'01_Assumptions'!C33-1)<='01_Assumptions'!$E$18,"Amber","Red"))))) | D27: =IF('01_Assumptions'!D33=0,"—",IF('01_Assumptions'!$D$18="H",IF('02_Actuals'!D11>='01_Assumptions'!D33,"Green",IF('02_Actuals'!D11>='01_Assumptions'!D33*(1-'01_Assumptions'!$E$18),"Amber","Red")),IF('01_Assumptions'!$D$18="L",IF('02_Actuals'!D11<='01_Assumptions'!D33,"Green",IF('02_Actuals'!D11<='01_Assumptions'!D33*(1+'01_Assumptions'!$E$18),"Amber","Red")),IF(ABS('02_Actuals'!D11/'01_Assumptions'!D33-1)<='01_Assumptions'!$F$18,"Green",IF(ABS('02_Actuals'!D11/'01_Assumptions'!D33-1)<='01_Assumptions'!$E$18,"Amber","Red"))))) | E27: =IF('01_Assumptions'!E33=0,"—",IF('01_Assumptions'!$D$18="H",IF('02_Actuals'!E11>='01_Assumptions'!E33,"Green",IF('02_Actuals'!E11>='01_Assumptions'!E33*(1-'01_Assumptions'!$E$18),"Amber","Red")),IF('01_Assumptions'!$D$18="L",IF('02_Actuals'!E11<='01_Assumptions'!E33,"Green",IF('02_Actuals'!E11<='01_Assumptions'!E33*(1+'01_Assumptions'!$E$18),"Amber","Red")),IF(ABS('02_Actuals'!E11/'01_Assumptions'!E33-1)<='01_Assumptions'!$F$18,"Green",IF(ABS('02_Actuals'!E11/'01_Assumptions'!E33-1)<='01_Assumptions'!$E$18,"Amber","Red"))))) | F27: =IF('01_Assumptions'!F33=0,"—",IF('01_Assumptions'!$D$18="H",IF('02_Actuals'!F11>='01_Assumptions'!F33,"Green",IF('02_Actuals'!F11>='01_Assumptions'!F33*(1-'01_Assumptions'!$E$18),"Amber","Red")),IF('01_Assumptions'!$D$18="L",IF('02_Actuals'!F11<='01_Assumptions'!F33,"Green",IF('02_Actuals'!F11<='01_Assumptions'!F33*(1+'01_Assumptions'!$E$18),"Amber","Red")),IF(ABS('02_Actuals'!F11/'01_Assumptions'!F33-1)<='01_Assumptions'!$F$18,"Green",IF(ABS('02_Actuals'!F11/'01_Assumptions'!F33-1)<='01_Assumptions'!$E$18,"Amber","Red"))))) | G27: =IF('01_Assumptions'!G33=0,"—",IF('01_Assumptions'!$D$18="H",IF('02_Actuals'!G11>='01_Assumptions'!G33,"Green",IF('02_Actuals'!G11>='01_Assumptions'!G33*(1-'01_Assumptions'!$E$18),"Amber","Red")),IF('01_Assumptions'!$D$18="L",IF('02_Actuals'!G11<='01_Assumptions'!G33,"Green",IF('02_Actuals'!G11<='01_Assumptions'!G33*(1+'01_Assumptions'!$E$18),"Amber","Red")),IF(ABS('02_Actuals'!G11/'01_Assumptions'!G33-1)<='01_Assumptions'!$F$18,"Green",IF(ABS('02_Actuals'!G11/'01_Assumptions'!G33-1)<='01_Assumptions'!$E$18,"Amber","Red"))))) | H27: =IF('01_Assumptions'!H33=0,"—",IF('01_Assumptions'!$D$18="H",IF('02_Actuals'!H11>='01_Assumptions'!H33,"Green",IF('02_Actuals'!H11>='01_Assumptions'!H33*(1-'01_Assumptions'!$E$18),"Amber","Red")),IF('01_Assumptions'!$D$18="L",IF('02_Actuals'!H11<='01_Assumptions'!H33,"Green",IF('02_Actuals'!H11<='01_Assumptions'!H33*(1+'01_Assumptions'!$E$18),"Amber","Red")),IF(ABS('02_Actuals'!H11/'01_Assumptions'!H33-1)<='01_Assumptions'!$F$18,"Green",IF(ABS('02_Actuals'!H11/'01_Assumptions'!H33-1)<='01_Assumptions'!$E$18,"Amber","Red"))))) | I27: =IF('01_Assumptions'!I33=0,"—",IF('01_Assumptions'!$D$18="H",IF('02_Actuals'!I11>='01_Assumptions'!I33,"Green",IF('02_Actuals'!I11>='01_Assumptions'!I33*(1-'01_Assumptions'!$E$18),"Amber","Red")),IF('01_Assumptions'!$D$18="L",IF('02_Actuals'!I11<='01_Assumptions'!I33,"Green",IF('02_Actuals'!I11<='01_Assumptions'!I33*(1+'01_Assumptions'!$E$18),"Amber","Red")),IF(ABS('02_Actuals'!I11/'01_Assumptions'!I33-1)<='01_Assumptions'!$F$18,"Green",IF(ABS('02_Actuals'!I11/'01_Assumptions'!I33-1)<='01_Assumptions'!$E$18,"Amber","Red"))))) | J27: =IF('01_Assumptions'!J33=0,"—",IF('01_Assumptions'!$D$18="H",IF('02_Actuals'!J11>='01_Assumptions'!J33,"Green",IF('02_Actuals'!J11>='01_Assumptions'!J33*(1-'01_Assumptions'!$E$18),"Amber","Red")),IF('01_Assumptions'!$D$18="L",IF('02_Actuals'!J11<='01_Assumptions'!J33,"Green",IF('02_Actuals'!J11<='01_Assumptions'!J33*(1+'01_Assumptions'!$E$18),"Amber","Red")),IF(ABS('02_Actuals'!J11/'01_Assumptions'!J33-1)<='01_Assumptions'!$F$18,"Green",IF(ABS('02_Actuals'!J11/'01_Assumptions'!J33-1)<='01_Assumptions'!$E$18,"Amber","Red"))))) | ... N27: =IF('01_Assumptions'!N33=0,"—",IF('01_Assumptions'!$D$18="H",IF('02_Actuals'!N11>='01_Assumptions'!N33,"Green",IF('02_Actuals'!N11>='01_Assumptions'!N33*(1-'01_Assumptions'!$E$18),"Amber","Red")),IF('01_Assumptions'!$D$18="L",IF('02_Actuals'!N11<='01_Assumptions'!N33,"Green",IF('02_Actuals'!N11<='01_Assumptions'!N33*(1+'01_Assumptions'!$E$18),"Amber","Red")),IF(ABS('02_Actuals'!N11/'01_Assumptions'!N33-1)<='01_Assumptions'!$F$18,"Green",IF(ABS('02_Actuals'!N11/'01_Assumptions'!N33-1)<='01_Assumptions'!$E$18,"Amber","Red")))))
B28: Scrap % | C28: =IF('01_Assumptions'!C34=0,"—",IF('01_Assumptions'!$D$19="H",IF('02_Actuals'!C12>='01_Assumptions'!C34,"Green",IF('02_Actuals'!C12>='01_Assumptions'!C34*(1-'01_Assumptions'!$E$19),"Amber","Red")),IF('01_Assumptions'!$D$19="L",IF('02_Actuals'!C12<='01_Assumptions'!C34,"Green",IF('02_Actuals'!C12<='01_Assumptions'!C34*(1+'01_Assumptions'!$E$19),"Amber","Red")),IF(ABS('02_Actuals'!C12/'01_Assumptions'!C34-1)<='01_Assumptions'!$F$19,"Green",IF(ABS('02_Actuals'!C12/'01_Assumptions'!C34-1)<='01_Assumptions'!$E$19,"Amber","Red"))))) | D28: =IF('01_Assumptions'!D34=0,"—",IF('01_Assumptions'!$D$19="H",IF('02_Actuals'!D12>='01_Assumptions'!D34,"Green",IF('02_Actuals'!D12>='01_Assumptions'!D34*(1-'01_Assumptions'!$E$19),"Amber","Red")),IF('01_Assumptions'!$D$19="L",IF('02_Actuals'!D12<='01_Assumptions'!D34,"Green",IF('02_Actuals'!D12<='01_Assumptions'!D34*(1+'01_Assumptions'!$E$19),"Amber","Red")),IF(ABS('02_Actuals'!D12/'01_Assumptions'!D34-1)<='01_Assumptions'!$F$19,"Green",IF(ABS('02_Actuals'!D12/'01_Assumptions'!D34-1)<='01_Assumptions'!$E$19,"Amber","Red"))))) | E28: =IF('01_Assumptions'!E34=0,"—",IF('01_Assumptions'!$D$19="H",IF('02_Actuals'!E12>='01_Assumptions'!E34,"Green",IF('02_Actuals'!E12>='01_Assumptions'!E34*(1-'01_Assumptions'!$E$19),"Amber","Red")),IF('01_Assumptions'!$D$19="L",IF('02_Actuals'!E12<='01_Assumptions'!E34,"Green",IF('02_Actuals'!E12<='01_Assumptions'!E34*(1+'01_Assumptions'!$E$19),"Amber","Red")),IF(ABS('02_Actuals'!E12/'01_Assumptions'!E34-1)<='01_Assumptions'!$F$19,"Green",IF(ABS('02_Actuals'!E12/'01_Assumptions'!E34-1)<='01_Assumptions'!$E$19,"Amber","Red"))))) | F28: =IF('01_Assumptions'!F34=0,"—",IF('01_Assumptions'!$D$19="H",IF('02_Actuals'!F12>='01_Assumptions'!F34,"Green",IF('02_Actuals'!F12>='01_Assumptions'!F34*(1-'01_Assumptions'!$E$19),"Amber","Red")),IF('01_Assumptions'!$D$19="L",IF('02_Actuals'!F12<='01_Assumptions'!F34,"Green",IF('02_Actuals'!F12<='01_Assumptions'!F34*(1+'01_Assumptions'!$E$19),"Amber","Red")),IF(ABS('02_Actuals'!F12/'01_Assumptions'!F34-1)<='01_Assumptions'!$F$19,"Green",IF(ABS('02_Actuals'!F12/'01_Assumptions'!F34-1)<='01_Assumptions'!$E$19,"Amber","Red"))))) | G28: =IF('01_Assumptions'!G34=0,"—",IF('01_Assumptions'!$D$19="H",IF('02_Actuals'!G12>='01_Assumptions'!G34,"Green",IF('02_Actuals'!G12>='01_Assumptions'!G34*(1-'01_Assumptions'!$E$19),"Amber","Red")),IF('01_Assumptions'!$D$19="L",IF('02_Actuals'!G12<='01_Assumptions'!G34,"Green",IF('02_Actuals'!G12<='01_Assumptions'!G34*(1+'01_Assumptions'!$E$19),"Amber","Red")),IF(ABS('02_Actuals'!G12/'01_Assumptions'!G34-1)<='01_Assumptions'!$F$19,"Green",IF(ABS('02_Actuals'!G12/'01_Assumptions'!G34-1)<='01_Assumptions'!$E$19,"Amber","Red"))))) | H28: =IF('01_Assumptions'!H34=0,"—",IF('01_Assumptions'!$D$19="H",IF('02_Actuals'!H12>='01_Assumptions'!H34,"Green",IF('02_Actuals'!H12>='01_Assumptions'!H34*(1-'01_Assumptions'!$E$19),"Amber","Red")),IF('01_Assumptions'!$D$19="L",IF('02_Actuals'!H12<='01_Assumptions'!H34,"Green",IF('02_Actuals'!H12<='01_Assumptions'!H34*(1+'01_Assumptions'!$E$19),"Amber","Red")),IF(ABS('02_Actuals'!H12/'01_Assumptions'!H34-1)<='01_Assumptions'!$F$19,"Green",IF(ABS('02_Actuals'!H12/'01_Assumptions'!H34-1)<='01_Assumptions'!$E$19,"Amber","Red"))))) | I28: =IF('01_Assumptions'!I34=0,"—",IF('01_Assumptions'!$D$19="H",IF('02_Actuals'!I12>='01_Assumptions'!I34,"Green",IF('02_Actuals'!I12>='01_Assumptions'!I34*(1-'01_Assumptions'!$E$19),"Amber","Red")),IF('01_Assumptions'!$D$19="L",IF('02_Actuals'!I12<='01_Assumptions'!I34,"Green",IF('02_Actuals'!I12<='01_Assumptions'!I34*(1+'01_Assumptions'!$E$19),"Amber","Red")),IF(ABS('02_Actuals'!I12/'01_Assumptions'!I34-1)<='01_Assumptions'!$F$19,"Green",IF(ABS('02_Actuals'!I12/'01_Assumptions'!I34-1)<='01_Assumptions'!$E$19,"Amber","Red"))))) | J28: =IF('01_Assumptions'!J34=0,"—",IF('01_Assumptions'!$D$19="H",IF('02_Actuals'!J12>='01_Assumptions'!J34,"Green",IF('02_Actuals'!J12>='01_Assumptions'!J34*(1-'01_Assumptions'!$E$19),"Amber","Red")),IF('01_Assumptions'!$D$19="L",IF('02_Actuals'!J12<='01_Assumptions'!J34,"Green",IF('02_Actuals'!J12<='01_Assumptions'!J34*(1+'01_Assumptions'!$E$19),"Amber","Red")),IF(ABS('02_Actuals'!J12/'01_Assumptions'!J34-1)<='01_Assumptions'!$F$19,"Green",IF(ABS('02_Actuals'!J12/'01_Assumptions'!J34-1)<='01_Assumptions'!$E$19,"Amber","Red"))))) | ... N28: =IF('01_Assumptions'!N34=0,"—",IF('01_Assumptions'!$D$19="H",IF('02_Actuals'!N12>='01_Assumptions'!N34,"Green",IF('02_Actuals'!N12>='01_Assumptions'!N34*(1-'01_Assumptions'!$E$19),"Amber","Red")),IF('01_Assumptions'!$D$19="L",IF('02_Actuals'!N12<='01_Assumptions'!N34,"Green",IF('02_Actuals'!N12<='01_Assumptions'!N34*(1+'01_Assumptions'!$E$19),"Amber","Red")),IF(ABS('02_Actuals'!N12/'01_Assumptions'!N34-1)<='01_Assumptions'!$F$19,"Green",IF(ABS('02_Actuals'!N12/'01_Assumptions'!N34-1)<='01_Assumptions'!$E$19,"Amber","Red")))))
B29: DSO | C29: =IF('01_Assumptions'!C35=0,"—",IF('01_Assumptions'!$D$20="H",IF('02_Actuals'!C13>='01_Assumptions'!C35,"Green",IF('02_Actuals'!C13>='01_Assumptions'!C35*(1-'01_Assumptions'!$E$20),"Amber","Red")),IF('01_Assumptions'!$D$20="L",IF('02_Actuals'!C13<='01_Assumptions'!C35,"Green",IF('02_Actuals'!C13<='01_Assumptions'!C35*(1+'01_Assumptions'!$E$20),"Amber","Red")),IF(ABS('02_Actuals'!C13/'01_Assumptions'!C35-1)<='01_Assumptions'!$F$20,"Green",IF(ABS('02_Actuals'!C13/'01_Assumptions'!C35-1)<='01_Assumptions'!$E$20,"Amber","Red"))))) | D29: =IF('01_Assumptions'!D35=0,"—",IF('01_Assumptions'!$D$20="H",IF('02_Actuals'!D13>='01_Assumptions'!D35,"Green",IF('02_Actuals'!D13>='01_Assumptions'!D35*(1-'01_Assumptions'!$E$20),"Amber","Red")),IF('01_Assumptions'!$D$20="L",IF('02_Actuals'!D13<='01_Assumptions'!D35,"Green",IF('02_Actuals'!D13<='01_Assumptions'!D35*(1+'01_Assumptions'!$E$20),"Amber","Red")),IF(ABS('02_Actuals'!D13/'01_Assumptions'!D35-1)<='01_Assumptions'!$F$20,"Green",IF(ABS('02_Actuals'!D13/'01_Assumptions'!D35-1)<='01_Assumptions'!$E$20,"Amber","Red"))))) | E29: =IF('01_Assumptions'!E35=0,"—",IF('01_Assumptions'!$D$20="H",IF('02_Actuals'!E13>='01_Assumptions'!E35,"Green",IF('02_Actuals'!E13>='01_Assumptions'!E35*(1-'01_Assumptions'!$E$20),"Amber","Red")),IF('01_Assumptions'!$D$20="L",IF('02_Actuals'!E13<='01_Assumptions'!E35,"Green",IF('02_Actuals'!E13<='01_Assumptions'!E35*(1+'01_Assumptions'!$E$20),"Amber","Red")),IF(ABS('02_Actuals'!E13/'01_Assumptions'!E35-1)<='01_Assumptions'!$F$20,"Green",IF(ABS('02_Actuals'!E13/'01_Assumptions'!E35-1)<='01_Assumptions'!$E$20,"Amber","Red"))))) | F29: =IF('01_Assumptions'!F35=0,"—",IF('01_Assumptions'!$D$20="H",IF('02_Actuals'!F13>='01_Assumptions'!F35,"Green",IF('02_Actuals'!F13>='01_Assumptions'!F35*(1-'01_Assumptions'!$E$20),"Amber","Red")),IF('01_Assumptions'!$D$20="L",IF('02_Actuals'!F13<='01_Assumptions'!F35,"Green",IF('02_Actuals'!F13<='01_Assumptions'!F35*(1+'01_Assumptions'!$E$20),"Amber","Red")),IF(ABS('02_Actuals'!F13/'01_Assumptions'!F35-1)<='01_Assumptions'!$F$20,"Green",IF(ABS('02_Actuals'!F13/'01_Assumptions'!F35-1)<='01_Assumptions'!$E$20,"Amber","Red"))))) | G29: =IF('01_Assumptions'!G35=0,"—",IF('01_Assumptions'!$D$20="H",IF('02_Actuals'!G13>='01_Assumptions'!G35,"Green",IF('02_Actuals'!G13>='01_Assumptions'!G35*(1-'01_Assumptions'!$E$20),"Amber","Red")),IF('01_Assumptions'!$D$20="L",IF('02_Actuals'!G13<='01_Assumptions'!G35,"Green",IF('02_Actuals'!G13<='01_Assumptions'!G35*(1+'01_Assumptions'!$E$20),"Amber","Red")),IF(ABS('02_Actuals'!G13/'01_Assumptions'!G35-1)<='01_Assumptions'!$F$20,"Green",IF(ABS('02_Actuals'!G13/'01_Assumptions'!G35-1)<='01_Assumptions'!$E$20,"Amber","Red"))))) | H29: =IF('01_Assumptions'!H35=0,"—",IF('01_Assumptions'!$D$20="H",IF('02_Actuals'!H13>='01_Assumptions'!H35,"Green",IF('02_Actuals'!H13>='01_Assumptions'!H35*(1-'01_Assumptions'!$E$20),"Amber","Red")),IF('01_Assumptions'!$D$20="L",IF('02_Actuals'!H13<='01_Assumptions'!H35,"Green",IF('02_Actuals'!H13<='01_Assumptions'!H35*(1+'01_Assumptions'!$E$20),"Amber","Red")),IF(ABS('02_Actuals'!H13/'01_Assumptions'!H35-1)<='01_Assumptions'!$F$20,"Green",IF(ABS('02_Actuals'!H13/'01_Assumptions'!H35-1)<='01_Assumptions'!$E$20,"Amber","Red"))))) | I29: =IF('01_Assumptions'!I35=0,"—",IF('01_Assumptions'!$D$20="H",IF('02_Actuals'!I13>='01_Assumptions'!I35,"Green",IF('02_Actuals'!I13>='01_Assumptions'!I35*(1-'01_Assumptions'!$E$20),"Amber","Red")),IF('01_Assumptions'!$D$20="L",IF('02_Actuals'!I13<='01_Assumptions'!I35,"Green",IF('02_Actuals'!I13<='01_Assumptions'!I35*(1+'01_Assumptions'!$E$20),"Amber","Red")),IF(ABS('02_Actuals'!I13/'01_Assumptions'!I35-1)<='01_Assumptions'!$F$20,"Green",IF(ABS('02_Actuals'!I13/'01_Assumptions'!I35-1)<='01_Assumptions'!$E$20,"Amber","Red"))))) | J29: =IF('01_Assumptions'!J35=0,"—",IF('01_Assumptions'!$D$20="H",IF('02_Actuals'!J13>='01_Assumptions'!J35,"Green",IF('02_Actuals'!J13>='01_Assumptions'!J35*(1-'01_Assumptions'!$E$20),"Amber","Red")),IF('01_Assumptions'!$D$20="L",IF('02_Actuals'!J13<='01_Assumptions'!J35,"Green",IF('02_Actuals'!J13<='01_Assumptions'!J35*(1+'01_Assumptions'!$E$20),"Amber","Red")),IF(ABS('02_Actuals'!J13/'01_Assumptions'!J35-1)<='01_Assumptions'!$F$20,"Green",IF(ABS('02_Actuals'!J13/'01_Assumptions'!J35-1)<='01_Assumptions'!$E$20,"Amber","Red"))))) | ... N29: =IF('01_Assumptions'!N35=0,"—",IF('01_Assumptions'!$D$20="H",IF('02_Actuals'!N13>='01_Assumptions'!N35,"Green",IF('02_Actuals'!N13>='01_Assumptions'!N35*(1-'01_Assumptions'!$E$20),"Amber","Red")),IF('01_Assumptions'!$D$20="L",IF('02_Actuals'!N13<='01_Assumptions'!N35,"Green",IF('02_Actuals'!N13<='01_Assumptions'!N35*(1+'01_Assumptions'!$E$20),"Amber","Red")),IF(ABS('02_Actuals'!N13/'01_Assumptions'!N35-1)<='01_Assumptions'!$F$20,"Green",IF(ABS('02_Actuals'!N13/'01_Assumptions'!N35-1)<='01_Assumptions'!$E$20,"Amber","Red")))))
B30: CCC | C30: =IF('01_Assumptions'!C36=0,"—",IF('01_Assumptions'!$D$21="H",IF('02_Actuals'!C14>='01_Assumptions'!C36,"Green",IF('02_Actuals'!C14>='01_Assumptions'!C36*(1-'01_Assumptions'!$E$21),"Amber","Red")),IF('01_Assumptions'!$D$21="L",IF('02_Actuals'!C14<='01_Assumptions'!C36,"Green",IF('02_Actuals'!C14<='01_Assumptions'!C36*(1+'01_Assumptions'!$E$21),"Amber","Red")),IF(ABS('02_Actuals'!C14/'01_Assumptions'!C36-1)<='01_Assumptions'!$F$21,"Green",IF(ABS('02_Actuals'!C14/'01_Assumptions'!C36-1)<='01_Assumptions'!$E$21,"Amber","Red"))))) | D30: =IF('01_Assumptions'!D36=0,"—",IF('01_Assumptions'!$D$21="H",IF('02_Actuals'!D14>='01_Assumptions'!D36,"Green",IF('02_Actuals'!D14>='01_Assumptions'!D36*(1-'01_Assumptions'!$E$21),"Amber","Red")),IF('01_Assumptions'!$D$21="L",IF('02_Actuals'!D14<='01_Assumptions'!D36,"Green",IF('02_Actuals'!D14<='01_Assumptions'!D36*(1+'01_Assumptions'!$E$21),"Amber","Red")),IF(ABS('02_Actuals'!D14/'01_Assumptions'!D36-1)<='01_Assumptions'!$F$21,"Green",IF(ABS('02_Actuals'!D14/'01_Assumptions'!D36-1)<='01_Assumptions'!$E$21,"Amber","Red"))))) | E30: =IF('01_Assumptions'!E36=0,"—",IF('01_Assumptions'!$D$21="H",IF('02_Actuals'!E14>='01_Assumptions'!E36,"Green",IF('02_Actuals'!E14>='01_Assumptions'!E36*(1-'01_Assumptions'!$E$21),"Amber","Red")),IF('01_Assumptions'!$D$21="L",IF('02_Actuals'!E14<='01_Assumptions'!E36,"Green",IF('02_Actuals'!E14<='01_Assumptions'!E36*(1+'01_Assumptions'!$E$21),"Amber","Red")),IF(ABS('02_Actuals'!E14/'01_Assumptions'!E36-1)<='01_Assumptions'!$F$21,"Green",IF(ABS('02_Actuals'!E14/'01_Assumptions'!E36-1)<='01_Assumptions'!$E$21,"Amber","Red"))))) | F30: =IF('01_Assumptions'!F36=0,"—",IF('01_Assumptions'!$D$21="H",IF('02_Actuals'!F14>='01_Assumptions'!F36,"Green",IF('02_Actuals'!F14>='01_Assumptions'!F36*(1-'01_Assumptions'!$E$21),"Amber","Red")),IF('01_Assumptions'!$D$21="L",IF('02_Actuals'!F14<='01_Assumptions'!F36,"Green",IF('02_Actuals'!F14<='01_Assumptions'!F36*(1+'01_Assumptions'!$E$21),"Amber","Red")),IF(ABS('02_Actuals'!F14/'01_Assumptions'!F36-1)<='01_Assumptions'!$F$21,"Green",IF(ABS('02_Actuals'!F14/'01_Assumptions'!F36-1)<='01_Assumptions'!$E$21,"Amber","Red"))))) | G30: =IF('01_Assumptions'!G36=0,"—",IF('01_Assumptions'!$D$21="H",IF('02_Actuals'!G14>='01_Assumptions'!G36,"Green",IF('02_Actuals'!G14>='01_Assumptions'!G36*(1-'01_Assumptions'!$E$21),"Amber","Red")),IF('01_Assumptions'!$D$21="L",IF('02_Actuals'!G14<='01_Assumptions'!G36,"Green",IF('02_Actuals'!G14<='01_Assumptions'!G36*(1+'01_Assumptions'!$E$21),"Amber","Red")),IF(ABS('02_Actuals'!G14/'01_Assumptions'!G36-1)<='01_Assumptions'!$F$21,"Green",IF(ABS('02_Actuals'!G14/'01_Assumptions'!G36-1)<='01_Assumptions'!$E$21,"Amber","Red"))))) | H30: =IF('01_Assumptions'!H36=0,"—",IF('01_Assumptions'!$D$21="H",IF('02_Actuals'!H14>='01_Assumptions'!H36,"Green",IF('02_Actuals'!H14>='01_Assumptions'!H36*(1-'01_Assumptions'!$E$21),"Amber","Red")),IF('01_Assumptions'!$D$21="L",IF('02_Actuals'!H14<='01_Assumptions'!H36,"Green",IF('02_Actuals'!H14<='01_Assumptions'!H36*(1+'01_Assumptions'!$E$21),"Amber","Red")),IF(ABS('02_Actuals'!H14/'01_Assumptions'!H36-1)<='01_Assumptions'!$F$21,"Green",IF(ABS('02_Actuals'!H14/'01_Assumptions'!H36-1)<='01_Assumptions'!$E$21,"Amber","Red"))))) | I30: =IF('01_Assumptions'!I36=0,"—",IF('01_Assumptions'!$D$21="H",IF('02_Actuals'!I14>='01_Assumptions'!I36,"Green",IF('02_Actuals'!I14>='01_Assumptions'!I36*(1-'01_Assumptions'!$E$21),"Amber","Red")),IF('01_Assumptions'!$D$21="L",IF('02_Actuals'!I14<='01_Assumptions'!I36,"Green",IF('02_Actuals'!I14<='01_Assumptions'!I36*(1+'01_Assumptions'!$E$21),"Amber","Red")),IF(ABS('02_Actuals'!I14/'01_Assumptions'!I36-1)<='01_Assumptions'!$F$21,"Green",IF(ABS('02_Actuals'!I14/'01_Assumptions'!I36-1)<='01_Assumptions'!$E$21,"Amber","Red"))))) | J30: =IF('01_Assumptions'!J36=0,"—",IF('01_Assumptions'!$D$21="H",IF('02_Actuals'!J14>='01_Assumptions'!J36,"Green",IF('02_Actuals'!J14>='01_Assumptions'!J36*(1-'01_Assumptions'!$E$21),"Amber","Red")),IF('01_Assumptions'!$D$21="L",IF('02_Actuals'!J14<='01_Assumptions'!J36,"Green",IF('02_Actuals'!J14<='01_Assumptions'!J36*(1+'01_Assumptions'!$E$21),"Amber","Red")),IF(ABS('02_Actuals'!J14/'01_Assumptions'!J36-1)<='01_Assumptions'!$F$21,"Green",IF(ABS('02_Actuals'!J14/'01_Assumptions'!J36-1)<='01_Assumptions'!$E$21,"Amber","Red"))))) | ... N30: =IF('01_Assumptions'!N36=0,"—",IF('01_Assumptions'!$D$21="H",IF('02_Actuals'!N14>='01_Assumptions'!N36,"Green",IF('02_Actuals'!N14>='01_Assumptions'!N36*(1-'01_Assumptions'!$E$21),"Amber","Red")),IF('01_Assumptions'!$D$21="L",IF('02_Actuals'!N14<='01_Assumptions'!N36,"Green",IF('02_Actuals'!N14<='01_Assumptions'!N36*(1+'01_Assumptions'!$E$21),"Amber","Red")),IF(ABS('02_Actuals'!N14/'01_Assumptions'!N36-1)<='01_Assumptions'!$F$21,"Green",IF(ABS('02_Actuals'!N14/'01_Assumptions'!N36-1)<='01_Assumptions'!$E$21,"Amber","Red")))))
B31: Headcount | C31: =IF('01_Assumptions'!C37=0,"—",IF('01_Assumptions'!$D$22="H",IF('02_Actuals'!C15>='01_Assumptions'!C37,"Green",IF('02_Actuals'!C15>='01_Assumptions'!C37*(1-'01_Assumptions'!$E$22),"Amber","Red")),IF('01_Assumptions'!$D$22="L",IF('02_Actuals'!C15<='01_Assumptions'!C37,"Green",IF('02_Actuals'!C15<='01_Assumptions'!C37*(1+'01_Assumptions'!$E$22),"Amber","Red")),IF(ABS('02_Actuals'!C15/'01_Assumptions'!C37-1)<='01_Assumptions'!$F$22,"Green",IF(ABS('02_Actuals'!C15/'01_Assumptions'!C37-1)<='01_Assumptions'!$E$22,"Amber","Red"))))) | D31: =IF('01_Assumptions'!D37=0,"—",IF('01_Assumptions'!$D$22="H",IF('02_Actuals'!D15>='01_Assumptions'!D37,"Green",IF('02_Actuals'!D15>='01_Assumptions'!D37*(1-'01_Assumptions'!$E$22),"Amber","Red")),IF('01_Assumptions'!$D$22="L",IF('02_Actuals'!D15<='01_Assumptions'!D37,"Green",IF('02_Actuals'!D15<='01_Assumptions'!D37*(1+'01_Assumptions'!$E$22),"Amber","Red")),IF(ABS('02_Actuals'!D15/'01_Assumptions'!D37-1)<='01_Assumptions'!$F$22,"Green",IF(ABS('02_Actuals'!D15/'01_Assumptions'!D37-1)<='01_Assumptions'!$E$22,"Amber","Red"))))) | E31: =IF('01_Assumptions'!E37=0,"—",IF('01_Assumptions'!$D$22="H",IF('02_Actuals'!E15>='01_Assumptions'!E37,"Green",IF('02_Actuals'!E15>='01_Assumptions'!E37*(1-'01_Assumptions'!$E$22),"Amber","Red")),IF('01_Assumptions'!$D$22="L",IF('02_Actuals'!E15<='01_Assumptions'!E37,"Green",IF('02_Actuals'!E15<='01_Assumptions'!E37*(1+'01_Assumptions'!$E$22),"Amber","Red")),IF(ABS('02_Actuals'!E15/'01_Assumptions'!E37-1)<='01_Assumptions'!$F$22,"Green",IF(ABS('02_Actuals'!E15/'01_Assumptions'!E37-1)<='01_Assumptions'!$E$22,"Amber","Red"))))) | F31: =IF('01_Assumptions'!F37=0,"—",IF('01_Assumptions'!$D$22="H",IF('02_Actuals'!F15>='01_Assumptions'!F37,"Green",IF('02_Actuals'!F15>='01_Assumptions'!F37*(1-'01_Assumptions'!$E$22),"Amber","Red")),IF('01_Assumptions'!$D$22="L",IF('02_Actuals'!F15<='01_Assumptions'!F37,"Green",IF('02_Actuals'!F15<='01_Assumptions'!F37*(1+'01_Assumptions'!$E$22),"Amber","Red")),IF(ABS('02_Actuals'!F15/'01_Assumptions'!F37-1)<='01_Assumptions'!$F$22,"Green",IF(ABS('02_Actuals'!F15/'01_Assumptions'!F37-1)<='01_Assumptions'!$E$22,"Amber","Red"))))) | G31: =IF('01_Assumptions'!G37=0,"—",IF('01_Assumptions'!$D$22="H",IF('02_Actuals'!G15>='01_Assumptions'!G37,"Green",IF('02_Actuals'!G15>='01_Assumptions'!G37*(1-'01_Assumptions'!$E$22),"Amber","Red")),IF('01_Assumptions'!$D$22="L",IF('02_Actuals'!G15<='01_Assumptions'!G37,"Green",IF('02_Actuals'!G15<='01_Assumptions'!G37*(1+'01_Assumptions'!$E$22),"Amber","Red")),IF(ABS('02_Actuals'!G15/'01_Assumptions'!G37-1)<='01_Assumptions'!$F$22,"Green",IF(ABS('02_Actuals'!G15/'01_Assumptions'!G37-1)<='01_Assumptions'!$E$22,"Amber","Red"))))) | H31: =IF('01_Assumptions'!H37=0,"—",IF('01_Assumptions'!$D$22="H",IF('02_Actuals'!H15>='01_Assumptions'!H37,"Green",IF('02_Actuals'!H15>='01_Assumptions'!H37*(1-'01_Assumptions'!$E$22),"Amber","Red")),IF('01_Assumptions'!$D$22="L",IF('02_Actuals'!H15<='01_Assumptions'!H37,"Green",IF('02_Actuals'!H15<='01_Assumptions'!H37*(1+'01_Assumptions'!$E$22),"Amber","Red")),IF(ABS('02_Actuals'!H15/'01_Assumptions'!H37-1)<='01_Assumptions'!$F$22,"Green",IF(ABS('02_Actuals'!H15/'01_Assumptions'!H37-1)<='01_Assumptions'!$E$22,"Amber","Red"))))) | I31: =IF('01_Assumptions'!I37=0,"—",IF('01_Assumptions'!$D$22="H",IF('02_Actuals'!I15>='01_Assumptions'!I37,"Green",IF('02_Actuals'!I15>='01_Assumptions'!I37*(1-'01_Assumptions'!$E$22),"Amber","Red")),IF('01_Assumptions'!$D$22="L",IF('02_Actuals'!I15<='01_Assumptions'!I37,"Green",IF('02_Actuals'!I15<='01_Assumptions'!I37*(1+'01_Assumptions'!$E$22),"Amber","Red")),IF(ABS('02_Actuals'!I15/'01_Assumptions'!I37-1)<='01_Assumptions'!$F$22,"Green",IF(ABS('02_Actuals'!I15/'01_Assumptions'!I37-1)<='01_Assumptions'!$E$22,"Amber","Red"))))) | J31: =IF('01_Assumptions'!J37=0,"—",IF('01_Assumptions'!$D$22="H",IF('02_Actuals'!J15>='01_Assumptions'!J37,"Green",IF('02_Actuals'!J15>='01_Assumptions'!J37*(1-'01_Assumptions'!$E$22),"Amber","Red")),IF('01_Assumptions'!$D$22="L",IF('02_Actuals'!J15<='01_Assumptions'!J37,"Green",IF('02_Actuals'!J15<='01_Assumptions'!J37*(1+'01_Assumptions'!$E$22),"Amber","Red")),IF(ABS('02_Actuals'!J15/'01_Assumptions'!J37-1)<='01_Assumptions'!$F$22,"Green",IF(ABS('02_Actuals'!J15/'01_Assumptions'!J37-1)<='01_Assumptions'!$E$22,"Amber","Red"))))) | ... N31: =IF('01_Assumptions'!N37=0,"—",IF('01_Assumptions'!$D$22="H",IF('02_Actuals'!N15>='01_Assumptions'!N37,"Green",IF('02_Actuals'!N15>='01_Assumptions'!N37*(1-'01_Assumptions'!$E$22),"Amber","Red")),IF('01_Assumptions'!$D$22="L",IF('02_Actuals'!N15<='01_Assumptions'!N37,"Green",IF('02_Actuals'!N15<='01_Assumptions'!N37*(1+'01_Assumptions'!$E$22),"Amber","Red")),IF(ABS('02_Actuals'!N15/'01_Assumptions'!N37-1)<='01_Assumptions'!$F$22,"Green",IF(ABS('02_Actuals'!N15/'01_Assumptions'!N37-1)<='01_Assumptions'!$E$22,"Amber","Red")))))
B32: Attrition % (ann.) | C32: =IF('01_Assumptions'!C38=0,"—",IF('01_Assumptions'!$D$23="H",IF('02_Actuals'!C16>='01_Assumptions'!C38,"Green",IF('02_Actuals'!C16>='01_Assumptions'!C38*(1-'01_Assumptions'!$E$23),"Amber","Red")),IF('01_Assumptions'!$D$23="L",IF('02_Actuals'!C16<='01_Assumptions'!C38,"Green",IF('02_Actuals'!C16<='01_Assumptions'!C38*(1+'01_Assumptions'!$E$23),"Amber","Red")),IF(ABS('02_Actuals'!C16/'01_Assumptions'!C38-1)<='01_Assumptions'!$F$23,"Green",IF(ABS('02_Actuals'!C16/'01_Assumptions'!C38-1)<='01_Assumptions'!$E$23,"Amber","Red"))))) | D32: =IF('01_Assumptions'!D38=0,"—",IF('01_Assumptions'!$D$23="H",IF('02_Actuals'!D16>='01_Assumptions'!D38,"Green",IF('02_Actuals'!D16>='01_Assumptions'!D38*(1-'01_Assumptions'!$E$23),"Amber","Red")),IF('01_Assumptions'!$D$23="L",IF('02_Actuals'!D16<='01_Assumptions'!D38,"Green",IF('02_Actuals'!D16<='01_Assumptions'!D38*(1+'01_Assumptions'!$E$23),"Amber","Red")),IF(ABS('02_Actuals'!D16/'01_Assumptions'!D38-1)<='01_Assumptions'!$F$23,"Green",IF(ABS('02_Actuals'!D16/'01_Assumptions'!D38-1)<='01_Assumptions'!$E$23,"Amber","Red"))))) | E32: =IF('01_Assumptions'!E38=0,"—",IF('01_Assumptions'!$D$23="H",IF('02_Actuals'!E16>='01_Assumptions'!E38,"Green",IF('02_Actuals'!E16>='01_Assumptions'!E38*(1-'01_Assumptions'!$E$23),"Amber","Red")),IF('01_Assumptions'!$D$23="L",IF('02_Actuals'!E16<='01_Assumptions'!E38,"Green",IF('02_Actuals'!E16<='01_Assumptions'!E38*(1+'01_Assumptions'!$E$23),"Amber","Red")),IF(ABS('02_Actuals'!E16/'01_Assumptions'!E38-1)<='01_Assumptions'!$F$23,"Green",IF(ABS('02_Actuals'!E16/'01_Assumptions'!E38-1)<='01_Assumptions'!$E$23,"Amber","Red"))))) | F32: =IF('01_Assumptions'!F38=0,"—",IF('01_Assumptions'!$D$23="H",IF('02_Actuals'!F16>='01_Assumptions'!F38,"Green",IF('02_Actuals'!F16>='01_Assumptions'!F38*(1-'01_Assumptions'!$E$23),"Amber","Red")),IF('01_Assumptions'!$D$23="L",IF('02_Actuals'!F16<='01_Assumptions'!F38,"Green",IF('02_Actuals'!F16<='01_Assumptions'!F38*(1+'01_Assumptions'!$E$23),"Amber","Red")),IF(ABS('02_Actuals'!F16/'01_Assumptions'!F38-1)<='01_Assumptions'!$F$23,"Green",IF(ABS('02_Actuals'!F16/'01_Assumptions'!F38-1)<='01_Assumptions'!$E$23,"Amber","Red"))))) | G32: =IF('01_Assumptions'!G38=0,"—",IF('01_Assumptions'!$D$23="H",IF('02_Actuals'!G16>='01_Assumptions'!G38,"Green",IF('02_Actuals'!G16>='01_Assumptions'!G38*(1-'01_Assumptions'!$E$23),"Amber","Red")),IF('01_Assumptions'!$D$23="L",IF('02_Actuals'!G16<='01_Assumptions'!G38,"Green",IF('02_Actuals'!G16<='01_Assumptions'!G38*(1+'01_Assumptions'!$E$23),"Amber","Red")),IF(ABS('02_Actuals'!G16/'01_Assumptions'!G38-1)<='01_Assumptions'!$F$23,"Green",IF(ABS('02_Actuals'!G16/'01_Assumptions'!G38-1)<='01_Assumptions'!$E$23,"Amber","Red"))))) | H32: =IF('01_Assumptions'!H38=0,"—",IF('01_Assumptions'!$D$23="H",IF('02_Actuals'!H16>='01_Assumptions'!H38,"Green",IF('02_Actuals'!H16>='01_Assumptions'!H38*(1-'01_Assumptions'!$E$23),"Amber","Red")),IF('01_Assumptions'!$D$23="L",IF('02_Actuals'!H16<='01_Assumptions'!H38,"Green",IF('02_Actuals'!H16<='01_Assumptions'!H38*(1+'01_Assumptions'!$E$23),"Amber","Red")),IF(ABS('02_Actuals'!H16/'01_Assumptions'!H38-1)<='01_Assumptions'!$F$23,"Green",IF(ABS('02_Actuals'!H16/'01_Assumptions'!H38-1)<='01_Assumptions'!$E$23,"Amber","Red"))))) | I32: =IF('01_Assumptions'!I38=0,"—",IF('01_Assumptions'!$D$23="H",IF('02_Actuals'!I16>='01_Assumptions'!I38,"Green",IF('02_Actuals'!I16>='01_Assumptions'!I38*(1-'01_Assumptions'!$E$23),"Amber","Red")),IF('01_Assumptions'!$D$23="L",IF('02_Actuals'!I16<='01_Assumptions'!I38,"Green",IF('02_Actuals'!I16<='01_Assumptions'!I38*(1+'01_Assumptions'!$E$23),"Amber","Red")),IF(ABS('02_Actuals'!I16/'01_Assumptions'!I38-1)<='01_Assumptions'!$F$23,"Green",IF(ABS('02_Actuals'!I16/'01_Assumptions'!I38-1)<='01_Assumptions'!$E$23,"Amber","Red"))))) | J32: =IF('01_Assumptions'!J38=0,"—",IF('01_Assumptions'!$D$23="H",IF('02_Actuals'!J16>='01_Assumptions'!J38,"Green",IF('02_Actuals'!J16>='01_Assumptions'!J38*(1-'01_Assumptions'!$E$23),"Amber","Red")),IF('01_Assumptions'!$D$23="L",IF('02_Actuals'!J16<='01_Assumptions'!J38,"Green",IF('02_Actuals'!J16<='01_Assumptions'!J38*(1+'01_Assumptions'!$E$23),"Amber","Red")),IF(ABS('02_Actuals'!J16/'01_Assumptions'!J38-1)<='01_Assumptions'!$F$23,"Green",IF(ABS('02_Actuals'!J16/'01_Assumptions'!J38-1)<='01_Assumptions'!$E$23,"Amber","Red"))))) | ... N32: =IF('01_Assumptions'!N38=0,"—",IF('01_Assumptions'!$D$23="H",IF('02_Actuals'!N16>='01_Assumptions'!N38,"Green",IF('02_Actuals'!N16>='01_Assumptions'!N38*(1-'01_Assumptions'!$E$23),"Amber","Red")),IF('01_Assumptions'!$D$23="L",IF('02_Actuals'!N16<='01_Assumptions'!N38,"Green",IF('02_Actuals'!N16<='01_Assumptions'!N38*(1+'01_Assumptions'!$E$23),"Amber","Red")),IF(ABS('02_Actuals'!N16/'01_Assumptions'!N38-1)<='01_Assumptions'!$F$23,"Green",IF(ABS('02_Actuals'!N16/'01_Assumptions'!N38-1)<='01_Assumptions'!$E$23,"Amber","Red")))))
B33: Operating cash flow | C33: =IF('01_Assumptions'!C39=0,"—",IF('01_Assumptions'!$D$24="H",IF('02_Actuals'!C17>='01_Assumptions'!C39,"Green",IF('02_Actuals'!C17>='01_Assumptions'!C39*(1-'01_Assumptions'!$E$24),"Amber","Red")),IF('01_Assumptions'!$D$24="L",IF('02_Actuals'!C17<='01_Assumptions'!C39,"Green",IF('02_Actuals'!C17<='01_Assumptions'!C39*(1+'01_Assumptions'!$E$24),"Amber","Red")),IF(ABS('02_Actuals'!C17/'01_Assumptions'!C39-1)<='01_Assumptions'!$F$24,"Green",IF(ABS('02_Actuals'!C17/'01_Assumptions'!C39-1)<='01_Assumptions'!$E$24,"Amber","Red"))))) | D33: =IF('01_Assumptions'!D39=0,"—",IF('01_Assumptions'!$D$24="H",IF('02_Actuals'!D17>='01_Assumptions'!D39,"Green",IF('02_Actuals'!D17>='01_Assumptions'!D39*(1-'01_Assumptions'!$E$24),"Amber","Red")),IF('01_Assumptions'!$D$24="L",IF('02_Actuals'!D17<='01_Assumptions'!D39,"Green",IF('02_Actuals'!D17<='01_Assumptions'!D39*(1+'01_Assumptions'!$E$24),"Amber","Red")),IF(ABS('02_Actuals'!D17/'01_Assumptions'!D39-1)<='01_Assumptions'!$F$24,"Green",IF(ABS('02_Actuals'!D17/'01_Assumptions'!D39-1)<='01_Assumptions'!$E$24,"Amber","Red"))))) | E33: =IF('01_Assumptions'!E39=0,"—",IF('01_Assumptions'!$D$24="H",IF('02_Actuals'!E17>='01_Assumptions'!E39,"Green",IF('02_Actuals'!E17>='01_Assumptions'!E39*(1-'01_Assumptions'!$E$24),"Amber","Red")),IF('01_Assumptions'!$D$24="L",IF('02_Actuals'!E17<='01_Assumptions'!E39,"Green",IF('02_Actuals'!E17<='01_Assumptions'!E39*(1+'01_Assumptions'!$E$24),"Amber","Red")),IF(ABS('02_Actuals'!E17/'01_Assumptions'!E39-1)<='01_Assumptions'!$F$24,"Green",IF(ABS('02_Actuals'!E17/'01_Assumptions'!E39-1)<='01_Assumptions'!$E$24,"Amber","Red"))))) | F33: =IF('01_Assumptions'!F39=0,"—",IF('01_Assumptions'!$D$24="H",IF('02_Actuals'!F17>='01_Assumptions'!F39,"Green",IF('02_Actuals'!F17>='01_Assumptions'!F39*(1-'01_Assumptions'!$E$24),"Amber","Red")),IF('01_Assumptions'!$D$24="L",IF('02_Actuals'!F17<='01_Assumptions'!F39,"Green",IF('02_Actuals'!F17<='01_Assumptions'!F39*(1+'01_Assumptions'!$E$24),"Amber","Red")),IF(ABS('02_Actuals'!F17/'01_Assumptions'!F39-1)<='01_Assumptions'!$F$24,"Green",IF(ABS('02_Actuals'!F17/'01_Assumptions'!F39-1)<='01_Assumptions'!$E$24,"Amber","Red"))))) | G33: =IF('01_Assumptions'!G39=0,"—",IF('01_Assumptions'!$D$24="H",IF('02_Actuals'!G17>='01_Assumptions'!G39,"Green",IF('02_Actuals'!G17>='01_Assumptions'!G39*(1-'01_Assumptions'!$E$24),"Amber","Red")),IF('01_Assumptions'!$D$24="L",IF('02_Actuals'!G17<='01_Assumptions'!G39,"Green",IF('02_Actuals'!G17<='01_Assumptions'!G39*(1+'01_Assumptions'!$E$24),"Amber","Red")),IF(ABS('02_Actuals'!G17/'01_Assumptions'!G39-1)<='01_Assumptions'!$F$24,"Green",IF(ABS('02_Actuals'!G17/'01_Assumptions'!G39-1)<='01_Assumptions'!$E$24,"Amber","Red"))))) | H33: =IF('01_Assumptions'!H39=0,"—",IF('01_Assumptions'!$D$24="H",IF('02_Actuals'!H17>='01_Assumptions'!H39,"Green",IF('02_Actuals'!H17>='01_Assumptions'!H39*(1-'01_Assumptions'!$E$24),"Amber","Red")),IF('01_Assumptions'!$D$24="L",IF('02_Actuals'!H17<='01_Assumptions'!H39,"Green",IF('02_Actuals'!H17<='01_Assumptions'!H39*(1+'01_Assumptions'!$E$24),"Amber","Red")),IF(ABS('02_Actuals'!H17/'01_Assumptions'!H39-1)<='01_Assumptions'!$F$24,"Green",IF(ABS('02_Actuals'!H17/'01_Assumptions'!H39-1)<='01_Assumptions'!$E$24,"Amber","Red"))))) | I33: =IF('01_Assumptions'!I39=0,"—",IF('01_Assumptions'!$D$24="H",IF('02_Actuals'!I17>='01_Assumptions'!I39,"Green",IF('02_Actuals'!I17>='01_Assumptions'!I39*(1-'01_Assumptions'!$E$24),"Amber","Red")),IF('01_Assumptions'!$D$24="L",IF('02_Actuals'!I17<='01_Assumptions'!I39,"Green",IF('02_Actuals'!I17<='01_Assumptions'!I39*(1+'01_Assumptions'!$E$24),"Amber","Red")),IF(ABS('02_Actuals'!I17/'01_Assumptions'!I39-1)<='01_Assumptions'!$F$24,"Green",IF(ABS('02_Actuals'!I17/'01_Assumptions'!I39-1)<='01_Assumptions'!$E$24,"Amber","Red"))))) | J33: =IF('01_Assumptions'!J39=0,"—",IF('01_Assumptions'!$D$24="H",IF('02_Actuals'!J17>='01_Assumptions'!J39,"Green",IF('02_Actuals'!J17>='01_Assumptions'!J39*(1-'01_Assumptions'!$E$24),"Amber","Red")),IF('01_Assumptions'!$D$24="L",IF('02_Actuals'!J17<='01_Assumptions'!J39,"Green",IF('02_Actuals'!J17<='01_Assumptions'!J39*(1+'01_Assumptions'!$E$24),"Amber","Red")),IF(ABS('02_Actuals'!J17/'01_Assumptions'!J39-1)<='01_Assumptions'!$F$24,"Green",IF(ABS('02_Actuals'!J17/'01_Assumptions'!J39-1)<='01_Assumptions'!$E$24,"Amber","Red"))))) | ... N33: =IF('01_Assumptions'!N39=0,"—",IF('01_Assumptions'!$D$24="H",IF('02_Actuals'!N17>='01_Assumptions'!N39,"Green",IF('02_Actuals'!N17>='01_Assumptions'!N39*(1-'01_Assumptions'!$E$24),"Amber","Red")),IF('01_Assumptions'!$D$24="L",IF('02_Actuals'!N17<='01_Assumptions'!N39,"Green",IF('02_Actuals'!N17<='01_Assumptions'!N39*(1+'01_Assumptions'!$E$24),"Amber","Red")),IF(ABS('02_Actuals'!N17/'01_Assumptions'!N39-1)<='01_Assumptions'!$F$24,"Green",IF(ABS('02_Actuals'!N17/'01_Assumptions'!N39-1)<='01_Assumptions'!$E$24,"Amber","Red")))))
B34: SG&A % of sales | C34: =IF('01_Assumptions'!C40=0,"—",IF('01_Assumptions'!$D$25="H",IF('02_Actuals'!C18>='01_Assumptions'!C40,"Green",IF('02_Actuals'!C18>='01_Assumptions'!C40*(1-'01_Assumptions'!$E$25),"Amber","Red")),IF('01_Assumptions'!$D$25="L",IF('02_Actuals'!C18<='01_Assumptions'!C40,"Green",IF('02_Actuals'!C18<='01_Assumptions'!C40*(1+'01_Assumptions'!$E$25),"Amber","Red")),IF(ABS('02_Actuals'!C18/'01_Assumptions'!C40-1)<='01_Assumptions'!$F$25,"Green",IF(ABS('02_Actuals'!C18/'01_Assumptions'!C40-1)<='01_Assumptions'!$E$25,"Amber","Red"))))) | D34: =IF('01_Assumptions'!D40=0,"—",IF('01_Assumptions'!$D$25="H",IF('02_Actuals'!D18>='01_Assumptions'!D40,"Green",IF('02_Actuals'!D18>='01_Assumptions'!D40*(1-'01_Assumptions'!$E$25),"Amber","Red")),IF('01_Assumptions'!$D$25="L",IF('02_Actuals'!D18<='01_Assumptions'!D40,"Green",IF('02_Actuals'!D18<='01_Assumptions'!D40*(1+'01_Assumptions'!$E$25),"Amber","Red")),IF(ABS('02_Actuals'!D18/'01_Assumptions'!D40-1)<='01_Assumptions'!$F$25,"Green",IF(ABS('02_Actuals'!D18/'01_Assumptions'!D40-1)<='01_Assumptions'!$E$25,"Amber","Red"))))) | E34: =IF('01_Assumptions'!E40=0,"—",IF('01_Assumptions'!$D$25="H",IF('02_Actuals'!E18>='01_Assumptions'!E40,"Green",IF('02_Actuals'!E18>='01_Assumptions'!E40*(1-'01_Assumptions'!$E$25),"Amber","Red")),IF('01_Assumptions'!$D$25="L",IF('02_Actuals'!E18<='01_Assumptions'!E40,"Green",IF('02_Actuals'!E18<='01_Assumptions'!E40*(1+'01_Assumptions'!$E$25),"Amber","Red")),IF(ABS('02_Actuals'!E18/'01_Assumptions'!E40-1)<='01_Assumptions'!$F$25,"Green",IF(ABS('02_Actuals'!E18/'01_Assumptions'!E40-1)<='01_Assumptions'!$E$25,"Amber","Red"))))) | F34: =IF('01_Assumptions'!F40=0,"—",IF('01_Assumptions'!$D$25="H",IF('02_Actuals'!F18>='01_Assumptions'!F40,"Green",IF('02_Actuals'!F18>='01_Assumptions'!F40*(1-'01_Assumptions'!$E$25),"Amber","Red")),IF('01_Assumptions'!$D$25="L",IF('02_Actuals'!F18<='01_Assumptions'!F40,"Green",IF('02_Actuals'!F18<='01_Assumptions'!F40*(1+'01_Assumptions'!$E$25),"Amber","Red")),IF(ABS('02_Actuals'!F18/'01_Assumptions'!F40-1)<='01_Assumptions'!$F$25,"Green",IF(ABS('02_Actuals'!F18/'01_Assumptions'!F40-1)<='01_Assumptions'!$E$25,"Amber","Red"))))) | G34: =IF('01_Assumptions'!G40=0,"—",IF('01_Assumptions'!$D$25="H",IF('02_Actuals'!G18>='01_Assumptions'!G40,"Green",IF('02_Actuals'!G18>='01_Assumptions'!G40*(1-'01_Assumptions'!$E$25),"Amber","Red")),IF('01_Assumptions'!$D$25="L",IF('02_Actuals'!G18<='01_Assumptions'!G40,"Green",IF('02_Actuals'!G18<='01_Assumptions'!G40*(1+'01_Assumptions'!$E$25),"Amber","Red")),IF(ABS('02_Actuals'!G18/'01_Assumptions'!G40-1)<='01_Assumptions'!$F$25,"Green",IF(ABS('02_Actuals'!G18/'01_Assumptions'!G40-1)<='01_Assumptions'!$E$25,"Amber","Red"))))) | H34: =IF('01_Assumptions'!H40=0,"—",IF('01_Assumptions'!$D$25="H",IF('02_Actuals'!H18>='01_Assumptions'!H40,"Green",IF('02_Actuals'!H18>='01_Assumptions'!H40*(1-'01_Assumptions'!$E$25),"Amber","Red")),IF('01_Assumptions'!$D$25="L",IF('02_Actuals'!H18<='01_Assumptions'!H40,"Green",IF('02_Actuals'!H18<='01_Assumptions'!H40*(1+'01_Assumptions'!$E$25),"Amber","Red")),IF(ABS('02_Actuals'!H18/'01_Assumptions'!H40-1)<='01_Assumptions'!$F$25,"Green",IF(ABS('02_Actuals'!H18/'01_Assumptions'!H40-1)<='01_Assumptions'!$E$25,"Amber","Red"))))) | I34: =IF('01_Assumptions'!I40=0,"—",IF('01_Assumptions'!$D$25="H",IF('02_Actuals'!I18>='01_Assumptions'!I40,"Green",IF('02_Actuals'!I18>='01_Assumptions'!I40*(1-'01_Assumptions'!$E$25),"Amber","Red")),IF('01_Assumptions'!$D$25="L",IF('02_Actuals'!I18<='01_Assumptions'!I40,"Green",IF('02_Actuals'!I18<='01_Assumptions'!I40*(1+'01_Assumptions'!$E$25),"Amber","Red")),IF(ABS('02_Actuals'!I18/'01_Assumptions'!I40-1)<='01_Assumptions'!$F$25,"Green",IF(ABS('02_Actuals'!I18/'01_Assumptions'!I40-1)<='01_Assumptions'!$E$25,"Amber","Red"))))) | J34: =IF('01_Assumptions'!J40=0,"—",IF('01_Assumptions'!$D$25="H",IF('02_Actuals'!J18>='01_Assumptions'!J40,"Green",IF('02_Actuals'!J18>='01_Assumptions'!J40*(1-'01_Assumptions'!$E$25),"Amber","Red")),IF('01_Assumptions'!$D$25="L",IF('02_Actuals'!J18<='01_Assumptions'!J40,"Green",IF('02_Actuals'!J18<='01_Assumptions'!J40*(1+'01_Assumptions'!$E$25),"Amber","Red")),IF(ABS('02_Actuals'!J18/'01_Assumptions'!J40-1)<='01_Assumptions'!$F$25,"Green",IF(ABS('02_Actuals'!J18/'01_Assumptions'!J40-1)<='01_Assumptions'!$E$25,"Amber","Red"))))) | ... N34: =IF('01_Assumptions'!N40=0,"—",IF('01_Assumptions'!$D$25="H",IF('02_Actuals'!N18>='01_Assumptions'!N40,"Green",IF('02_Actuals'!N18>='01_Assumptions'!N40*(1-'01_Assumptions'!$E$25),"Amber","Red")),IF('01_Assumptions'!$D$25="L",IF('02_Actuals'!N18<='01_Assumptions'!N40,"Green",IF('02_Actuals'!N18<='01_Assumptions'!N40*(1+'01_Assumptions'!$E$25),"Amber","Red")),IF(ABS('02_Actuals'!N18/'01_Assumptions'!N40-1)<='01_Assumptions'!$F$25,"Green",IF(ABS('02_Actuals'!N18/'01_Assumptions'!N40-1)<='01_Assumptions'!$E$25,"Amber","Red")))))
B36: Monthly variance % (actual / target − 1)
C37: Jan-26 | D37: Feb-26 | E37: Mar-26 | F37: Apr-26 | G37: May-26 | H37: Jun-26 | I37: Jul-26 | J37: Aug-26 | K37: Sep-26 | L37: Oct-26 | M37: Nov-26 | N37: Dec-26
B38: Net revenue | C38: =IF('01_Assumptions'!C29=0,"—",'02_Actuals'!C7/'01_Assumptions'!C29-1) | D38: =IF('01_Assumptions'!D29=0,"—",'02_Actuals'!D7/'01_Assumptions'!D29-1) | E38: =IF('01_Assumptions'!E29=0,"—",'02_Actuals'!E7/'01_Assumptions'!E29-1) | F38: =IF('01_Assumptions'!F29=0,"—",'02_Actuals'!F7/'01_Assumptions'!F29-1) | G38: =IF('01_Assumptions'!G29=0,"—",'02_Actuals'!G7/'01_Assumptions'!G29-1) | H38: =IF('01_Assumptions'!H29=0,"—",'02_Actuals'!H7/'01_Assumptions'!H29-1) | I38: =IF('01_Assumptions'!I29=0,"—",'02_Actuals'!I7/'01_Assumptions'!I29-1) | J38: =IF('01_Assumptions'!J29=0,"—",'02_Actuals'!J7/'01_Assumptions'!J29-1) | ... N38: =IF('01_Assumptions'!N29=0,"—",'02_Actuals'!N7/'01_Assumptions'!N29-1)
B39: Gross margin % | C39: =IF('01_Assumptions'!C30=0,"—",'02_Actuals'!C8/'01_Assumptions'!C30-1) | D39: =IF('01_Assumptions'!D30=0,"—",'02_Actuals'!D8/'01_Assumptions'!D30-1) | E39: =IF('01_Assumptions'!E30=0,"—",'02_Actuals'!E8/'01_Assumptions'!E30-1) | F39: =IF('01_Assumptions'!F30=0,"—",'02_Actuals'!F8/'01_Assumptions'!F30-1) | G39: =IF('01_Assumptions'!G30=0,"—",'02_Actuals'!G8/'01_Assumptions'!G30-1) | H39: =IF('01_Assumptions'!H30=0,"—",'02_Actuals'!H8/'01_Assumptions'!H30-1) | I39: =IF('01_Assumptions'!I30=0,"—",'02_Actuals'!I8/'01_Assumptions'!I30-1) | J39: =IF('01_Assumptions'!J30=0,"—",'02_Actuals'!J8/'01_Assumptions'!J30-1) | ... N39: =IF('01_Assumptions'!N30=0,"—",'02_Actuals'!N8/'01_Assumptions'!N30-1)
B40: EBITDA | C40: =IF('01_Assumptions'!C31=0,"—",'02_Actuals'!C9/'01_Assumptions'!C31-1) | D40: =IF('01_Assumptions'!D31=0,"—",'02_Actuals'!D9/'01_Assumptions'!D31-1) | E40: =IF('01_Assumptions'!E31=0,"—",'02_Actuals'!E9/'01_Assumptions'!E31-1) | F40: =IF('01_Assumptions'!F31=0,"—",'02_Actuals'!F9/'01_Assumptions'!F31-1) | G40: =IF('01_Assumptions'!G31=0,"—",'02_Actuals'!G9/'01_Assumptions'!G31-1) | H40: =IF('01_Assumptions'!H31=0,"—",'02_Actuals'!H9/'01_Assumptions'!H31-1) | I40: =IF('01_Assumptions'!I31=0,"—",'02_Actuals'!I9/'01_Assumptions'!I31-1) | J40: =IF('01_Assumptions'!J31=0,"—",'02_Actuals'!J9/'01_Assumptions'!J31-1) | ... N40: =IF('01_Assumptions'!N31=0,"—",'02_Actuals'!N9/'01_Assumptions'!N31-1)
B41: Volume | C41: =IF('01_Assumptions'!C32=0,"—",'02_Actuals'!C10/'01_Assumptions'!C32-1) | D41: =IF('01_Assumptions'!D32=0,"—",'02_Actuals'!D10/'01_Assumptions'!D32-1) | E41: =IF('01_Assumptions'!E32=0,"—",'02_Actuals'!E10/'01_Assumptions'!E32-1) | F41: =IF('01_Assumptions'!F32=0,"—",'02_Actuals'!F10/'01_Assumptions'!F32-1) | G41: =IF('01_Assumptions'!G32=0,"—",'02_Actuals'!G10/'01_Assumptions'!G32-1) | H41: =IF('01_Assumptions'!H32=0,"—",'02_Actuals'!H10/'01_Assumptions'!H32-1) | I41: =IF('01_Assumptions'!I32=0,"—",'02_Actuals'!I10/'01_Assumptions'!I32-1) | J41: =IF('01_Assumptions'!J32=0,"—",'02_Actuals'!J10/'01_Assumptions'!J32-1) | ... N41: =IF('01_Assumptions'!N32=0,"—",'02_Actuals'!N10/'01_Assumptions'!N32-1)
B42: OTIF % | C42: =IF('01_Assumptions'!C33=0,"—",'02_Actuals'!C11/'01_Assumptions'!C33-1) | D42: =IF('01_Assumptions'!D33=0,"—",'02_Actuals'!D11/'01_Assumptions'!D33-1) | E42: =IF('01_Assumptions'!E33=0,"—",'02_Actuals'!E11/'01_Assumptions'!E33-1) | F42: =IF('01_Assumptions'!F33=0,"—",'02_Actuals'!F11/'01_Assumptions'!F33-1) | G42: =IF('01_Assumptions'!G33=0,"—",'02_Actuals'!G11/'01_Assumptions'!G33-1) | H42: =IF('01_Assumptions'!H33=0,"—",'02_Actuals'!H11/'01_Assumptions'!H33-1) | I42: =IF('01_Assumptions'!I33=0,"—",'02_Actuals'!I11/'01_Assumptions'!I33-1) | J42: =IF('01_Assumptions'!J33=0,"—",'02_Actuals'!J11/'01_Assumptions'!J33-1) | ... N42: =IF('01_Assumptions'!N33=0,"—",'02_Actuals'!N11/'01_Assumptions'!N33-1)
B43: Scrap % | C43: =IF('01_Assumptions'!C34=0,"—",'02_Actuals'!C12/'01_Assumptions'!C34-1) | D43: =IF('01_Assumptions'!D34=0,"—",'02_Actuals'!D12/'01_Assumptions'!D34-1) | E43: =IF('01_Assumptions'!E34=0,"—",'02_Actuals'!E12/'01_Assumptions'!E34-1) | F43: =IF('01_Assumptions'!F34=0,"—",'02_Actuals'!F12/'01_Assumptions'!F34-1) | G43: =IF('01_Assumptions'!G34=0,"—",'02_Actuals'!G12/'01_Assumptions'!G34-1) | H43: =IF('01_Assumptions'!H34=0,"—",'02_Actuals'!H12/'01_Assumptions'!H34-1) | I43: =IF('01_Assumptions'!I34=0,"—",'02_Actuals'!I12/'01_Assumptions'!I34-1) | J43: =IF('01_Assumptions'!J34=0,"—",'02_Actuals'!J12/'01_Assumptions'!J34-1) | ... N43: =IF('01_Assumptions'!N34=0,"—",'02_Actuals'!N12/'01_Assumptions'!N34-1)
B44: DSO | C44: =IF('01_Assumptions'!C35=0,"—",'02_Actuals'!C13/'01_Assumptions'!C35-1) | D44: =IF('01_Assumptions'!D35=0,"—",'02_Actuals'!D13/'01_Assumptions'!D35-1) | E44: =IF('01_Assumptions'!E35=0,"—",'02_Actuals'!E13/'01_Assumptions'!E35-1) | F44: =IF('01_Assumptions'!F35=0,"—",'02_Actuals'!F13/'01_Assumptions'!F35-1) | G44: =IF('01_Assumptions'!G35=0,"—",'02_Actuals'!G13/'01_Assumptions'!G35-1) | H44: =IF('01_Assumptions'!H35=0,"—",'02_Actuals'!H13/'01_Assumptions'!H35-1) | I44: =IF('01_Assumptions'!I35=0,"—",'02_Actuals'!I13/'01_Assumptions'!I35-1) | J44: =IF('01_Assumptions'!J35=0,"—",'02_Actuals'!J13/'01_Assumptions'!J35-1) | ... N44: =IF('01_Assumptions'!N35=0,"—",'02_Actuals'!N13/'01_Assumptions'!N35-1)
B45: CCC | C45: =IF('01_Assumptions'!C36=0,"—",'02_Actuals'!C14/'01_Assumptions'!C36-1) | D45: =IF('01_Assumptions'!D36=0,"—",'02_Actuals'!D14/'01_Assumptions'!D36-1) | E45: =IF('01_Assumptions'!E36=0,"—",'02_Actuals'!E14/'01_Assumptions'!E36-1) | F45: =IF('01_Assumptions'!F36=0,"—",'02_Actuals'!F14/'01_Assumptions'!F36-1) | G45: =IF('01_Assumptions'!G36=0,"—",'02_Actuals'!G14/'01_Assumptions'!G36-1) | H45: =IF('01_Assumptions'!H36=0,"—",'02_Actuals'!H14/'01_Assumptions'!H36-1) | I45: =IF('01_Assumptions'!I36=0,"—",'02_Actuals'!I14/'01_Assumptions'!I36-1) | J45: =IF('01_Assumptions'!J36=0,"—",'02_Actuals'!J14/'01_Assumptions'!J36-1) | ... N45: =IF('01_Assumptions'!N36=0,"—",'02_Actuals'!N14/'01_Assumptions'!N36-1)
B46: Headcount | C46: =IF('01_Assumptions'!C37=0,"—",'02_Actuals'!C15/'01_Assumptions'!C37-1) | D46: =IF('01_Assumptions'!D37=0,"—",'02_Actuals'!D15/'01_Assumptions'!D37-1) | E46: =IF('01_Assumptions'!E37=0,"—",'02_Actuals'!E15/'01_Assumptions'!E37-1) | F46: =IF('01_Assumptions'!F37=0,"—",'02_Actuals'!F15/'01_Assumptions'!F37-1) | G46: =IF('01_Assumptions'!G37=0,"—",'02_Actuals'!G15/'01_Assumptions'!G37-1) | H46: =IF('01_Assumptions'!H37=0,"—",'02_Actuals'!H15/'01_Assumptions'!H37-1) | I46: =IF('01_Assumptions'!I37=0,"—",'02_Actuals'!I15/'01_Assumptions'!I37-1) | J46: =IF('01_Assumptions'!J37=0,"—",'02_Actuals'!J15/'01_Assumptions'!J37-1) | ... N46: =IF('01_Assumptions'!N37=0,"—",'02_Actuals'!N15/'01_Assumptions'!N37-1)
B47: Attrition % (ann.) | C47: =IF('01_Assumptions'!C38=0,"—",'02_Actuals'!C16/'01_Assumptions'!C38-1) | D47: =IF('01_Assumptions'!D38=0,"—",'02_Actuals'!D16/'01_Assumptions'!D38-1) | E47: =IF('01_Assumptions'!E38=0,"—",'02_Actuals'!E16/'01_Assumptions'!E38-1) | F47: =IF('01_Assumptions'!F38=0,"—",'02_Actuals'!F16/'01_Assumptions'!F38-1) | G47: =IF('01_Assumptions'!G38=0,"—",'02_Actuals'!G16/'01_Assumptions'!G38-1) | H47: =IF('01_Assumptions'!H38=0,"—",'02_Actuals'!H16/'01_Assumptions'!H38-1) | I47: =IF('01_Assumptions'!I38=0,"—",'02_Actuals'!I16/'01_Assumptions'!I38-1) | J47: =IF('01_Assumptions'!J38=0,"—",'02_Actuals'!J16/'01_Assumptions'!J38-1) | ... N47: =IF('01_Assumptions'!N38=0,"—",'02_Actuals'!N16/'01_Assumptions'!N38-1)
B48: Operating cash flow | C48: =IF('01_Assumptions'!C39=0,"—",'02_Actuals'!C17/'01_Assumptions'!C39-1) | D48: =IF('01_Assumptions'!D39=0,"—",'02_Actuals'!D17/'01_Assumptions'!D39-1) | E48: =IF('01_Assumptions'!E39=0,"—",'02_Actuals'!E17/'01_Assumptions'!E39-1) | F48: =IF('01_Assumptions'!F39=0,"—",'02_Actuals'!F17/'01_Assumptions'!F39-1) | G48: =IF('01_Assumptions'!G39=0,"—",'02_Actuals'!G17/'01_Assumptions'!G39-1) | H48: =IF('01_Assumptions'!H39=0,"—",'02_Actuals'!H17/'01_Assumptions'!H39-1) | I48: =IF('01_Assumptions'!I39=0,"—",'02_Actuals'!I17/'01_Assumptions'!I39-1) | J48: =IF('01_Assumptions'!J39=0,"—",'02_Actuals'!J17/'01_Assumptions'!J39-1) | ... N48: =IF('01_Assumptions'!N39=0,"—",'02_Actuals'!N17/'01_Assumptions'!N39-1)
B49: SG&A % of sales | C49: =IF('01_Assumptions'!C40=0,"—",'02_Actuals'!C18/'01_Assumptions'!C40-1) | D49: =IF('01_Assumptions'!D40=0,"—",'02_Actuals'!D18/'01_Assumptions'!D40-1) | E49: =IF('01_Assumptions'!E40=0,"—",'02_Actuals'!E18/'01_Assumptions'!E40-1) | F49: =IF('01_Assumptions'!F40=0,"—",'02_Actuals'!F18/'01_Assumptions'!F40-1) | G49: =IF('01_Assumptions'!G40=0,"—",'02_Actuals'!G18/'01_Assumptions'!G40-1) | H49: =IF('01_Assumptions'!H40=0,"—",'02_Actuals'!H18/'01_Assumptions'!H40-1) | I49: =IF('01_Assumptions'!I40=0,"—",'02_Actuals'!I18/'01_Assumptions'!I40-1) | J49: =IF('01_Assumptions'!J40=0,"—",'02_Actuals'!J18/'01_Assumptions'!J40-1) | ... N49: =IF('01_Assumptions'!N40=0,"—",'02_Actuals'!N18/'01_Assumptions'!N40-1)
B51: Green / Amber / Red is computed, not typed. Change a target or an actual and the heatmap moves.

Sheet 04_Trends
B2: Trends — MoM, rolling 3-month, YTD, vs target
B3: All formulas off 02_Actuals and 01_Assumptions. In-cell bars are a simple sparkline substitute.
B5: Actuals (echo)
C6: Jan-26 | D6: Feb-26 | E6: Mar-26 | F6: Apr-26 | G6: May-26 | H6: Jun-26 | I6: Jul-26 | J6: Aug-26 | K6: Sep-26 | L6: Oct-26 | M6: Nov-26 | N6: Dec-26
B7: Net revenue | C7: ='02_Actuals'!C7 | D7: ='02_Actuals'!D7 | E7: ='02_Actuals'!E7 | F7: ='02_Actuals'!F7 | G7: ='02_Actuals'!G7 | H7: ='02_Actuals'!H7 | I7: ='02_Actuals'!I7 | J7: ='02_Actuals'!J7 | ... N7: ='02_Actuals'!N7
B8: Gross margin % | C8: ='02_Actuals'!C8 | D8: ='02_Actuals'!D8 | E8: ='02_Actuals'!E8 | F8: ='02_Actuals'!F8 | G8: ='02_Actuals'!G8 | H8: ='02_Actuals'!H8 | I8: ='02_Actuals'!I8 | J8: ='02_Actuals'!J8 | ... N8: ='02_Actuals'!N8
B9: EBITDA | C9: ='02_Actuals'!C9 | D9: ='02_Actuals'!D9 | E9: ='02_Actuals'!E9 | F9: ='02_Actuals'!F9 | G9: ='02_Actuals'!G9 | H9: ='02_Actuals'!H9 | I9: ='02_Actuals'!I9 | J9: ='02_Actuals'!J9 | ... N9: ='02_Actuals'!N9
B10: Volume | C10: ='02_Actuals'!C10 | D10: ='02_Actuals'!D10 | E10: ='02_Actuals'!E10 | F10: ='02_Actuals'!F10 | G10: ='02_Actuals'!G10 | H10: ='02_Actuals'!H10 | I10: ='02_Actuals'!I10 | J10: ='02_Actuals'!J10 | ... N10: ='02_Actuals'!N10
B11: OTIF % | C11: ='02_Actuals'!C11 | D11: ='02_Actuals'!D11 | E11: ='02_Actuals'!E11 | F11: ='02_Actuals'!F11 | G11: ='02_Actuals'!G11 | H11: ='02_Actuals'!H11 | I11: ='02_Actuals'!I11 | J11: ='02_Actuals'!J11 | ... N11: ='02_Actuals'!N11
B12: Scrap % | C12: ='02_Actuals'!C12 | D12: ='02_Actuals'!D12 | E12: ='02_Actuals'!E12 | F12: ='02_Actuals'!F12 | G12: ='02_Actuals'!G12 | H12: ='02_Actuals'!H12 | I12: ='02_Actuals'!I12 | J12: ='02_Actuals'!J12 | ... N12: ='02_Actuals'!N12
B13: DSO | C13: ='02_Actuals'!C13 | D13: ='02_Actuals'!D13 | E13: ='02_Actuals'!E13 | F13: ='02_Actuals'!F13 | G13: ='02_Actuals'!G13 | H13: ='02_Actuals'!H13 | I13: ='02_Actuals'!I13 | J13: ='02_Actuals'!J13 | ... N13: ='02_Actuals'!N13
B14: CCC | C14: ='02_Actuals'!C14 | D14: ='02_Actuals'!D14 | E14: ='02_Actuals'!E14 | F14: ='02_Actuals'!F14 | G14: ='02_Actuals'!G14 | H14: ='02_Actuals'!H14 | I14: ='02_Actuals'!I14 | J14: ='02_Actuals'!J14 | ... N14: ='02_Actuals'!N14
B15: Headcount | C15: ='02_Actuals'!C15 | D15: ='02_Actuals'!D15 | E15: ='02_Actuals'!E15 | F15: ='02_Actuals'!F15 | G15: ='02_Actuals'!G15 | H15: ='02_Actuals'!H15 | I15: ='02_Actuals'!I15 | J15: ='02_Actuals'!J15 | ... N15: ='02_Actuals'!N15
B16: Attrition % (ann.) | C16: ='02_Actuals'!C16 | D16: ='02_Actuals'!D16 | E16: ='02_Actuals'!E16 | F16: ='02_Actuals'!F16 | G16: ='02_Actuals'!G16 | H16: ='02_Actuals'!H16 | I16: ='02_Actuals'!I16 | J16: ='02_Actuals'!J16 | ... N16: ='02_Actuals'!N16
B17: Operating cash flow | C17: ='02_Actuals'!C17 | D17: ='02_Actuals'!D17 | E17: ='02_Actuals'!E17 | F17: ='02_Actuals'!F17 | G17: ='02_Actuals'!G17 | H17: ='02_Actuals'!H17 | I17: ='02_Actuals'!I17 | J17: ='02_Actuals'!J17 | ... N17: ='02_Actuals'!N17
B18: SG&A % of sales | C18: ='02_Actuals'!C18 | D18: ='02_Actuals'!D18 | E18: ='02_Actuals'!E18 | F18: ='02_Actuals'!F18 | G18: ='02_Actuals'!G18 | H18: ='02_Actuals'!H18 | I18: ='02_Actuals'!I18 | J18: ='02_Actuals'!J18 | ... N18: ='02_Actuals'!N18
B20: Month-on-month change
C21: Jan-26 | D21: Feb-26 | E21: Mar-26 | F21: Apr-26 | G21: May-26 | H21: Jun-26 | I21: Jul-26 | J21: Aug-26 | K21: Sep-26 | L21: Oct-26 | M21: Nov-26 | N21: Dec-26
B22: Net revenue | C22: — | D22: =IF(C7=0,"—",D7/C7-1) | E22: =IF(D7=0,"—",E7/D7-1) | F22: =IF(E7=0,"—",F7/E7-1) | G22: =IF(F7=0,"—",G7/F7-1) | H22: =IF(G7=0,"—",H7/G7-1) | I22: =IF(H7=0,"—",I7/H7-1) | J22: =IF(I7=0,"—",J7/I7-1) | K22: =IF(J7=0,"—",K7/J7-1) | ... N22: =IF(M7=0,"—",N7/M7-1)
B23: Gross margin % | C23: — | D23: =D8-C8 | E23: =E8-D8 | F23: =F8-E8 | G23: =G8-F8 | H23: =H8-G8 | I23: =I8-H8 | J23: =J8-I8 | K23: =K8-J8 | ... N23: =N8-M8
B24: EBITDA | C24: — | D24: =IF(C9=0,"—",D9/C9-1) | E24: =IF(D9=0,"—",E9/D9-1) | F24: =IF(E9=0,"—",F9/E9-1) | G24: =IF(F9=0,"—",G9/F9-1) | H24: =IF(G9=0,"—",H9/G9-1) | I24: =IF(H9=0,"—",I9/H9-1) | J24: =IF(I9=0,"—",J9/I9-1) | K24: =IF(J9=0,"—",K9/J9-1) | ... N24: =IF(M9=0,"—",N9/M9-1)
B25: Volume | C25: — | D25: =IF(C10=0,"—",D10/C10-1) | E25: =IF(D10=0,"—",E10/D10-1) | F25: =IF(E10=0,"—",F10/E10-1) | G25: =IF(F10=0,"—",G10/F10-1) | H25: =IF(G10=0,"—",H10/G10-1) | I25: =IF(H10=0,"—",I10/H10-1) | J25: =IF(I10=0,"—",J10/I10-1) | K25: =IF(J10=0,"—",K10/J10-1) | ... N25: =IF(M10=0,"—",N10/M10-1)
B26: OTIF % | C26: — | D26: =D11-C11 | E26: =E11-D11 | F26: =F11-E11 | G26: =G11-F11 | H26: =H11-G11 | I26: =I11-H11 | J26: =J11-I11 | K26: =K11-J11 | ... N26: =N11-M11
B27: Scrap % | C27: — | D27: =D12-C12 | E27: =E12-D12 | F27: =F12-E12 | G27: =G12-F12 | H27: =H12-G12 | I27: =I12-H12 | J27: =J12-I12 | K27: =K12-J12 | ... N27: =N12-M12
B28: DSO | C28: — | D28: =IF(C13=0,"—",D13/C13-1) | E28: =IF(D13=0,"—",E13/D13-1) | F28: =IF(E13=0,"—",F13/E13-1) | G28: =IF(F13=0,"—",G13/F13-1) | H28: =IF(G13=0,"—",H13/G13-1) | I28: =IF(H13=0,"—",I13/H13-1) | J28: =IF(I13=0,"—",J13/I13-1) | K28: =IF(J13=0,"—",K13/J13-1) | ... N28: =IF(M13=0,"—",N13/M13-1)
B29: CCC | C29: — | D29: =IF(C14=0,"—",D14/C14-1) | E29: =IF(D14=0,"—",E14/D14-1) | F29: =IF(E14=0,"—",F14/E14-1) | G29: =IF(F14=0,"—",G14/F14-1) | H29: =IF(G14=0,"—",H14/G14-1) | I29: =IF(H14=0,"—",I14/H14-1) | J29: =IF(I14=0,"—",J14/I14-1) | K29: =IF(J14=0,"—",K14/J14-1) | ... N29: =IF(M14=0,"—",N14/M14-1)
B30: Headcount | C30: — | D30: =IF(C15=0,"—",D15/C15-1) | E30: =IF(D15=0,"—",E15/D15-1) | F30: =IF(E15=0,"—",F15/E15-1) | G30: =IF(F15=0,"—",G15/F15-1) | H30: =IF(G15=0,"—",H15/G15-1) | I30: =IF(H15=0,"—",I15/H15-1) | J30: =IF(I15=0,"—",J15/I15-1) | K30: =IF(J15=0,"—",K15/J15-1) | ... N30: =IF(M15=0,"—",N15/M15-1)
B31: Attrition % (ann.) | C31: — | D31: =D16-C16 | E31: =E16-D16 | F31: =F16-E16 | G31: =G16-F16 | H31: =H16-G16 | I31: =I16-H16 | J31: =J16-I16 | K31: =K16-J16 | ... N31: =N16-M16
B32: Operating cash flow | C32: — | D32: =IF(C17=0,"—",D17/C17-1) | E32: =IF(D17=0,"—",E17/D17-1) | F32: =IF(E17=0,"—",F17/E17-1) | G32: =IF(F17=0,"—",G17/F17-1) | H32: =IF(G17=0,"—",H17/G17-1) | I32: =IF(H17=0,"—",I17/H17-1) | J32: =IF(I17=0,"—",J17/I17-1) | K32: =IF(J17=0,"—",K17/J17-1) | ... N32: =IF(M17=0,"—",N17/M17-1)
B33: SG&A % of sales | C33: — | D33: =D18-C18 | E33: =E18-D18 | F33: =F18-E18 | G33: =G18-F18 | H33: =H18-G18 | I33: =I18-H18 | J33: =J18-I18 | K33: =K18-J18 | ... N33: =N18-M18
B35: Rolling 3-month average
C36: Jan-26 | D36: Feb-26 | E36: Mar-26 | F36: Apr-26 | G36: May-26 | H36: Jun-26 | I36: Jul-26 | J36: Aug-26 | K36: Sep-26 | L36: Oct-26 | M36: Nov-26 | N36: Dec-26
B37: Net revenue | C37: =C7 | D37: =AVERAGE(C7:D7) | E37: =AVERAGE(C7:E7) | F37: =AVERAGE(D7:F7) | G37: =AVERAGE(E7:G7) | H37: =AVERAGE(F7:H7) | I37: =AVERAGE(G7:I7) | J37: =AVERAGE(H7:J7) | K37: =AVERAGE(I7:K7) | L37: =AVERAGE(J7:L7) | ... N37: =AVERAGE(L7:N7)
B38: Gross margin % | C38: =C8 | D38: =AVERAGE(C8:D8) | E38: =AVERAGE(C8:E8) | F38: =AVERAGE(D8:F8) | G38: =AVERAGE(E8:G8) | H38: =AVERAGE(F8:H8) | I38: =AVERAGE(G8:I8) | J38: =AVERAGE(H8:J8) | K38: =AVERAGE(I8:K8) | L38: =AVERAGE(J8:L8) | ... N38: =AVERAGE(L8:N8)
B39: EBITDA | C39: =C9 | D39: =AVERAGE(C9:D9) | E39: =AVERAGE(C9:E9) | F39: =AVERAGE(D9:F9) | G39: =AVERAGE(E9:G9) | H39: =AVERAGE(F9:H9) | I39: =AVERAGE(G9:I9) | J39: =AVERAGE(H9:J9) | K39: =AVERAGE(I9:K9) | L39: =AVERAGE(J9:L9) | ... N39: =AVERAGE(L9:N9)
B40: Volume | C40: =C10 | D40: =AVERAGE(C10:D10) | E40: =AVERAGE(C10:E10) | F40: =AVERAGE(D10:F10) | G40: =AVERAGE(E10:G10) | H40: =AVERAGE(F10:H10) | I40: =AVERAGE(G10:I10) | J40: =AVERAGE(H10:J10) | K40: =AVERAGE(I10:K10) | L40: =AVERAGE(J10:L10) | ... N40: =AVERAGE(L10:N10)
B41: OTIF % | C41: =C11 | D41: =AVERAGE(C11:D11) | E41: =AVERAGE(C11:E11) | F41: =AVERAGE(D11:F11) | G41: =AVERAGE(E11:G11) | H41: =AVERAGE(F11:H11) | I41: =AVERAGE(G11:I11) | J41: =AVERAGE(H11:J11) | K41: =AVERAGE(I11:K11) | L41: =AVERAGE(J11:L11) | ... N41: =AVERAGE(L11:N11)
B42: Scrap % | C42: =C12 | D42: =AVERAGE(C12:D12) | E42: =AVERAGE(C12:E12) | F42: =AVERAGE(D12:F12) | G42: =AVERAGE(E12:G12) | H42: =AVERAGE(F12:H12) | I42: =AVERAGE(G12:I12) | J42: =AVERAGE(H12:J12) | K42: =AVERAGE(I12:K12) | L42: =AVERAGE(J12:L12) | ... N42: =AVERAGE(L12:N12)
B43: DSO | C43: =C13 | D43: =AVERAGE(C13:D13) | E43: =AVERAGE(C13:E13) | F43: =AVERAGE(D13:F13) | G43: =AVERAGE(E13:G13) | H43: =AVERAGE(F13:H13) | I43: =AVERAGE(G13:I13) | J43: =AVERAGE(H13:J13) | K43: =AVERAGE(I13:K13) | L43: =AVERAGE(J13:L13) | ... N43: =AVERAGE(L13:N13)
B44: CCC | C44: =C14 | D44: =AVERAGE(C14:D14) | E44: =AVERAGE(C14:E14) | F44: =AVERAGE(D14:F14) | G44: =AVERAGE(E14:G14) | H44: =AVERAGE(F14:H14) | I44: =AVERAGE(G14:I14) | J44: =AVERAGE(H14:J14) | K44: =AVERAGE(I14:K14) | L44: =AVERAGE(J14:L14) | ... N44: =AVERAGE(L14:N14)
B45: Headcount | C45: =C15 | D45: =AVERAGE(C15:D15) | E45: =AVERAGE(C15:E15) | F45: =AVERAGE(D15:F15) | G45: =AVERAGE(E15:G15) | H45: =AVERAGE(F15:H15) | I45: =AVERAGE(G15:I15) | J45: =AVERAGE(H15:J15) | K45: =AVERAGE(I15:K15) | L45: =AVERAGE(J15:L15) | ... N45: =AVERAGE(L15:N15)
B46: Attrition % (ann.) | C46: =C16 | D46: =AVERAGE(C16:D16) | E46: =AVERAGE(C16:E16) | F46: =AVERAGE(D16:F16) | G46: =AVERAGE(E16:G16) | H46: =AVERAGE(F16:H16) | I46: =AVERAGE(G16:I16) | J46: =AVERAGE(H16:J16) | K46: =AVERAGE(I16:K16) | L46: =AVERAGE(J16:L16) | ... N46: =AVERAGE(L16:N16)
B47: Operating cash flow | C47: =C17 | D47: =AVERAGE(C17:D17) | E47: =AVERAGE(C17:E17) | F47: =AVERAGE(D17:F17) | G47: =AVERAGE(E17:G17) | H47: =AVERAGE(F17:H17) | I47: =AVERAGE(G17:I17) | J47: =AVERAGE(H17:J17) | K47: =AVERAGE(I17:K17) | L47: =AVERAGE(J17:L17) | ... N47: =AVERAGE(L17:N17)
B48: SG&A % of sales | C48: =C18 | D48: =AVERAGE(C18:D18) | E48: =AVERAGE(C18:E18) | F48: =AVERAGE(D18:F18) | G48: =AVERAGE(E18:G18) | H48: =AVERAGE(F18:H18) | I48: =AVERAGE(G18:I18) | J48: =AVERAGE(H18:J18) | K48: =AVERAGE(I18:K18) | L48: =AVERAGE(J18:L18) | ... N48: =AVERAGE(L18:N18)
B50: Variance vs monthly target
C51: Jan-26 | D51: Feb-26 | E51: Mar-26 | F51: Apr-26 | G51: May-26 | H51: Jun-26 | I51: Jul-26 | J51: Aug-26 | K51: Sep-26 | L51: Oct-26 | M51: Nov-26 | N51: Dec-26
B52: Net revenue | C52: ='02_Actuals'!C7-'01_Assumptions'!C29 | D52: ='02_Actuals'!D7-'01_Assumptions'!D29 | E52: ='02_Actuals'!E7-'01_Assumptions'!E29 | F52: ='02_Actuals'!F7-'01_Assumptions'!F29 | G52: ='02_Actuals'!G7-'01_Assumptions'!G29 | H52: ='02_Actuals'!H7-'01_Assumptions'!H29 | I52: ='02_Actuals'!I7-'01_Assumptions'!I29 | J52: ='02_Actuals'!J7-'01_Assumptions'!J29 | ... N52: ='02_Actuals'!N7-'01_Assumptions'!N29
B53: Gross margin % | C53: ='02_Actuals'!C8-'01_Assumptions'!C30 | D53: ='02_Actuals'!D8-'01_Assumptions'!D30 | E53: ='02_Actuals'!E8-'01_Assumptions'!E30 | F53: ='02_Actuals'!F8-'01_Assumptions'!F30 | G53: ='02_Actuals'!G8-'01_Assumptions'!G30 | H53: ='02_Actuals'!H8-'01_Assumptions'!H30 | I53: ='02_Actuals'!I8-'01_Assumptions'!I30 | J53: ='02_Actuals'!J8-'01_Assumptions'!J30 | ... N53: ='02_Actuals'!N8-'01_Assumptions'!N30
B54: EBITDA | C54: ='02_Actuals'!C9-'01_Assumptions'!C31 | D54: ='02_Actuals'!D9-'01_Assumptions'!D31 | E54: ='02_Actuals'!E9-'01_Assumptions'!E31 | F54: ='02_Actuals'!F9-'01_Assumptions'!F31 | G54: ='02_Actuals'!G9-'01_Assumptions'!G31 | H54: ='02_Actuals'!H9-'01_Assumptions'!H31 | I54: ='02_Actuals'!I9-'01_Assumptions'!I31 | J54: ='02_Actuals'!J9-'01_Assumptions'!J31 | ... N54: ='02_Actuals'!N9-'01_Assumptions'!N31
B55: Volume | C55: ='02_Actuals'!C10-'01_Assumptions'!C32 | D55: ='02_Actuals'!D10-'01_Assumptions'!D32 | E55: ='02_Actuals'!E10-'01_Assumptions'!E32 | F55: ='02_Actuals'!F10-'01_Assumptions'!F32 | G55: ='02_Actuals'!G10-'01_Assumptions'!G32 | H55: ='02_Actuals'!H10-'01_Assumptions'!H32 | I55: ='02_Actuals'!I10-'01_Assumptions'!I32 | J55: ='02_Actuals'!J10-'01_Assumptions'!J32 | ... N55: ='02_Actuals'!N10-'01_Assumptions'!N32
B56: OTIF % | C56: ='02_Actuals'!C11-'01_Assumptions'!C33 | D56: ='02_Actuals'!D11-'01_Assumptions'!D33 | E56: ='02_Actuals'!E11-'01_Assumptions'!E33 | F56: ='02_Actuals'!F11-'01_Assumptions'!F33 | G56: ='02_Actuals'!G11-'01_Assumptions'!G33 | H56: ='02_Actuals'!H11-'01_Assumptions'!H33 | I56: ='02_Actuals'!I11-'01_Assumptions'!I33 | J56: ='02_Actuals'!J11-'01_Assumptions'!J33 | ... N56: ='02_Actuals'!N11-'01_Assumptions'!N33
B57: Scrap % | C57: ='02_Actuals'!C12-'01_Assumptions'!C34 | D57: ='02_Actuals'!D12-'01_Assumptions'!D34 | E57: ='02_Actuals'!E12-'01_Assumptions'!E34 | F57: ='02_Actuals'!F12-'01_Assumptions'!F34 | G57: ='02_Actuals'!G12-'01_Assumptions'!G34 | H57: ='02_Actuals'!H12-'01_Assumptions'!H34 | I57: ='02_Actuals'!I12-'01_Assumptions'!I34 | J57: ='02_Actuals'!J12-'01_Assumptions'!J34 | ... N57: ='02_Actuals'!N12-'01_Assumptions'!N34
B58: DSO | C58: ='02_Actuals'!C13-'01_Assumptions'!C35 | D58: ='02_Actuals'!D13-'01_Assumptions'!D35 | E58: ='02_Actuals'!E13-'01_Assumptions'!E35 | F58: ='02_Actuals'!F13-'01_Assumptions'!F35 | G58: ='02_Actuals'!G13-'01_Assumptions'!G35 | H58: ='02_Actuals'!H13-'01_Assumptions'!H35 | I58: ='02_Actuals'!I13-'01_Assumptions'!I35 | J58: ='02_Actuals'!J13-'01_Assumptions'!J35 | ... N58: ='02_Actuals'!N13-'01_Assumptions'!N35
B59: CCC | C59: ='02_Actuals'!C14-'01_Assumptions'!C36 | D59: ='02_Actuals'!D14-'01_Assumptions'!D36 | E59: ='02_Actuals'!E14-'01_Assumptions'!E36 | F59: ='02_Actuals'!F14-'01_Assumptions'!F36 | G59: ='02_Actuals'!G14-'01_Assumptions'!G36 | H59: ='02_Actuals'!H14-'01_Assumptions'!H36 | I59: ='02_Actuals'!I14-'01_Assumptions'!I36 | J59: ='02_Actuals'!J14-'01_Assumptions'!J36 | ... N59: ='02_Actuals'!N14-'01_Assumptions'!N36
B60: Headcount | C60: ='02_Actuals'!C15-'01_Assumptions'!C37 | D60: ='02_Actuals'!D15-'01_Assumptions'!D37 | E60: ='02_Actuals'!E15-'01_Assumptions'!E37 | F60: ='02_Actuals'!F15-'01_Assumptions'!F37 | G60: ='02_Actuals'!G15-'01_Assumptions'!G37 | H60: ='02_Actuals'!H15-'01_Assumptions'!H37 | I60: ='02_Actuals'!I15-'01_Assumptions'!I37 | J60: ='02_Actuals'!J15-'01_Assumptions'!J37 | ... N60: ='02_Actuals'!N15-'01_Assumptions'!N37
B61: Attrition % (ann.) | C61: ='02_Actuals'!C16-'01_Assumptions'!C38 | D61: ='02_Actuals'!D16-'01_Assumptions'!D38 | E61: ='02_Actuals'!E16-'01_Assumptions'!E38 | F61: ='02_Actuals'!F16-'01_Assumptions'!F38 | G61: ='02_Actuals'!G16-'01_Assumptions'!G38 | H61: ='02_Actuals'!H16-'01_Assumptions'!H38 | I61: ='02_Actuals'!I16-'01_Assumptions'!I38 | J61: ='02_Actuals'!J16-'01_Assumptions'!J38 | ... N61: ='02_Actuals'!N16-'01_Assumptions'!N38
B62: Operating cash flow | C62: ='02_Actuals'!C17-'01_Assumptions'!C39 | D62: ='02_Actuals'!D17-'01_Assumptions'!D39 | E62: ='02_Actuals'!E17-'01_Assumptions'!E39 | F62: ='02_Actuals'!F17-'01_Assumptions'!F39 | G62: ='02_Actuals'!G17-'01_Assumptions'!G39 | H62: ='02_Actuals'!H17-'01_Assumptions'!H39 | I62: ='02_Actuals'!I17-'01_Assumptions'!I39 | J62: ='02_Actuals'!J17-'01_Assumptions'!J39 | ... N62: ='02_Actuals'!N17-'01_Assumptions'!N39
B63: SG&A % of sales | C63: ='02_Actuals'!C18-'01_Assumptions'!C40 | D63: ='02_Actuals'!D18-'01_Assumptions'!D40 | E63: ='02_Actuals'!E18-'01_Assumptions'!E40 | F63: ='02_Actuals'!F18-'01_Assumptions'!F40 | G63: ='02_Actuals'!G18-'01_Assumptions'!G40 | H63: ='02_Actuals'!H18-'01_Assumptions'!H40 | I63: ='02_Actuals'!I18-'01_Assumptions'!I40 | J63: ='02_Actuals'!J18-'01_Assumptions'!J40 | ... N63: ='02_Actuals'!N18-'01_Assumptions'!N40
B65: YoY revenue and volume vs FY25
C66: Jan-26 | D66: Feb-26 | E66: Mar-26 | F66: Apr-26 | G66: May-26 | H66: Jun-26 | I66: Jul-26 | J66: Aug-26 | K66: Sep-26 | L66: Oct-26 | M66: Nov-26 | N66: Dec-26
B67: Revenue YoY % | C67: =IF('01_Assumptions'!C44=0,"—",'02_Actuals'!C7/'01_Assumptions'!C44-1) | D67: =IF('01_Assumptions'!D44=0,"—",'02_Actuals'!D7/'01_Assumptions'!D44-1) | E67: =IF('01_Assumptions'!E44=0,"—",'02_Actuals'!E7/'01_Assumptions'!E44-1) | F67: =IF('01_Assumptions'!F44=0,"—",'02_Actuals'!F7/'01_Assumptions'!F44-1) | G67: =IF('01_Assumptions'!G44=0,"—",'02_Actuals'!G7/'01_Assumptions'!G44-1) | H67: =IF('01_Assumptions'!H44=0,"—",'02_Actuals'!H7/'01_Assumptions'!H44-1) | I67: =IF('01_Assumptions'!I44=0,"—",'02_Actuals'!I7/'01_Assumptions'!I44-1) | J67: =IF('01_Assumptions'!J44=0,"—",'02_Actuals'!J7/'01_Assumptions'!J44-1) | ... N67: =IF('01_Assumptions'!N44=0,"—",'02_Actuals'!N7/'01_Assumptions'!N44-1)
B68: Volume YoY % | C68: =IF('01_Assumptions'!C45=0,"—",'02_Actuals'!C10/'01_Assumptions'!C45-1) | D68: =IF('01_Assumptions'!D45=0,"—",'02_Actuals'!D10/'01_Assumptions'!D45-1) | E68: =IF('01_Assumptions'!E45=0,"—",'02_Actuals'!E10/'01_Assumptions'!E45-1) | F68: =IF('01_Assumptions'!F45=0,"—",'02_Actuals'!F10/'01_Assumptions'!F45-1) | G68: =IF('01_Assumptions'!G45=0,"—",'02_Actuals'!G10/'01_Assumptions'!G45-1) | H68: =IF('01_Assumptions'!H45=0,"—",'02_Actuals'!H10/'01_Assumptions'!H45-1) | I68: =IF('01_Assumptions'!I45=0,"—",'02_Actuals'!I10/'01_Assumptions'!I45-1) | J68: =IF('01_Assumptions'!J45=0,"—",'02_Actuals'!J10/'01_Assumptions'!J45-1) | ... N68: =IF('01_Assumptions'!N45=0,"—",'02_Actuals'!N10/'01_Assumptions'!N45-1)
B70: In-cell trend bars (revenue actual)
C71: Jan-26 | D71: Feb-26 | E71: Mar-26 | F71: Apr-26 | G71: May-26 | H71: Jun-26 | I71: Jul-26 | J71: Aug-26 | K71: Sep-26 | L71: Oct-26 | M71: Nov-26 | N71: Dec-26
B72: Revenue bar | C72: =REPT("█",MAX(0,ROUND(C7/8000,0))) | D72: =REPT("█",MAX(0,ROUND(D7/8000,0))) | E72: =REPT("█",MAX(0,ROUND(E7/8000,0))) | F72: =REPT("█",MAX(0,ROUND(F7/8000,0))) | G72: =REPT("█",MAX(0,ROUND(G7/8000,0))) | H72: =REPT("█",MAX(0,ROUND(H7/8000,0))) | I72: =REPT("█",MAX(0,ROUND(I7/8000,0))) | J72: =REPT("█",MAX(0,ROUND(J7/8000,0))) | ... N72: =REPT("█",MAX(0,ROUND(N7/8000,0)))
B73: OTIF bar | C73: =REPT("█",MAX(0,ROUND(C11*40,0))) | D73: =REPT("█",MAX(0,ROUND(D11*40,0))) | E73: =REPT("█",MAX(0,ROUND(E11*40,0))) | F73: =REPT("█",MAX(0,ROUND(F11*40,0))) | G73: =REPT("█",MAX(0,ROUND(G11*40,0))) | H73: =REPT("█",MAX(0,ROUND(H11*40,0))) | I73: =REPT("█",MAX(0,ROUND(I11*40,0))) | J73: =REPT("█",MAX(0,ROUND(J11*40,0))) | ... N73: =REPT("█",MAX(0,ROUND(N11*40,0)))
B74: CCC bar | C74: =REPT("█",MAX(0,ROUND(C14/8,0))) | D74: =REPT("█",MAX(0,ROUND(D14/8,0))) | E74: =REPT("█",MAX(0,ROUND(E14/8,0))) | F74: =REPT("█",MAX(0,ROUND(F14/8,0))) | G74: =REPT("█",MAX(0,ROUND(G14/8,0))) | H74: =REPT("█",MAX(0,ROUND(H14/8,0))) | I74: =REPT("█",MAX(0,ROUND(I14/8,0))) | J74: =REPT("█",MAX(0,ROUND(J14/8,0))) | ... N74: =REPT("█",MAX(0,ROUND(N14/8,0)))
B76: Revenue bar is scaled by $8m; OTIF by 2.5 pts per block; CCC by 8 days per block. Cosmetic only.

Sheet 05_Dashboard
B2: KPI dashboard
B3: As-of month | C3: ='01_Assumptions'!D5 | E3: Tiles pull the as-of month from the scorecard. RAG is a formula.
B5: Net revenue | F5: EBITDA | J5: OTIF %
B6: Actual | C6: ='03_Scorecard'!C8 | D6: ='03_Scorecard'!G8 | F6: Actual | G6: ='03_Scorecard'!C10 | H6: ='03_Scorecard'!G10 | J6: Actual | K6: ='03_Scorecard'!C12 | L6: ='03_Scorecard'!G12
B7: Target | C7: ='03_Scorecard'!D8 | F7: Target | G7: ='03_Scorecard'!D10 | J7: Target | K7: ='03_Scorecard'!D12
B8: Var / YTD RAG | C8: ='03_Scorecard'!E8 | D8: ='03_Scorecard'!K8 | F8: Var / YTD RAG | G8: ='03_Scorecard'!E10 | H8: ='03_Scorecard'!K10 | J8: Var / YTD RAG | K8: ='03_Scorecard'!E12 | L8: ='03_Scorecard'!K12
B11: CCC (days) | F11: Headcount | J11: Op. cash flow
B12: Actual | C12: ='03_Scorecard'!C15 | D12: ='03_Scorecard'!G15 | F12: Actual | G12: ='03_Scorecard'!C16 | H12: ='03_Scorecard'!G16 | J12: Actual | K12: ='03_Scorecard'!C18 | L12: ='03_Scorecard'!G18
B13: Target | C13: ='03_Scorecard'!D15 | F13: Target | G13: ='03_Scorecard'!D16 | J13: Target | K13: ='03_Scorecard'!D18
B14: Var / YTD RAG | C14: ='03_Scorecard'!E15 | D14: ='03_Scorecard'!K15 | F14: Var / YTD RAG | G14: ='03_Scorecard'!E16 | H14: ='03_Scorecard'!K16 | J14: Var / YTD RAG | K14: ='03_Scorecard'!E18 | L14: ='03_Scorecard'!K18
B16: Full as-of RAG strip
C17: Net revenue | D17: Gross margin % | E17: EBITDA | F17: Volume | G17: OTIF % | H17: Scrap % | I17: DSO | J17: CCC | K17: Headcount | L17: Attrition % (ann.) | M17: Operating cash flow | N17: SG&A % of sales
C18: ='03_Scorecard'!G8 | D18: ='03_Scorecard'!G9 | E18: ='03_Scorecard'!G10 | F18: ='03_Scorecard'!G11 | G18: ='03_Scorecard'!G12 | H18: ='03_Scorecard'!G13 | I18: ='03_Scorecard'!G14 | J18: ='03_Scorecard'!G15 | K18: ='03_Scorecard'!G16 | L18: ='03_Scorecard'!G17 | M18: ='03_Scorecard'!G18 | N18: ='03_Scorecard'!G19
B20: Chart data
B21: Metric | C21: Jan-26 | D21: Feb-26 | E21: Mar-26 | F21: Apr-26 | G21: May-26 | H21: Jun-26 | I21: Jul-26 | J21: Aug-26 | K21: Sep-26 | L21: Oct-26 | M21: Nov-26 | N21: Dec-26
B22: Revenue actual | C22: ='02_Actuals'!C7 | D22: ='02_Actuals'!D7 | E22: ='02_Actuals'!E7 | F22: ='02_Actuals'!F7 | G22: ='02_Actuals'!G7 | H22: ='02_Actuals'!H7 | I22: ='02_Actuals'!I7 | J22: ='02_Actuals'!J7 | ... N22: ='02_Actuals'!N7
B23: Revenue target | C23: ='01_Assumptions'!C29 | D23: ='01_Assumptions'!D29 | E23: ='01_Assumptions'!E29 | F23: ='01_Assumptions'!F29 | G23: ='01_Assumptions'!G29 | H23: ='01_Assumptions'!H29 | I23: ='01_Assumptions'!I29 | J23: ='01_Assumptions'!J29 | ... N23: ='01_Assumptions'!N29
B24: OTIF actual | C24: ='02_Actuals'!C11 | D24: ='02_Actuals'!D11 | E24: ='02_Actuals'!E11 | F24: ='02_Actuals'!F11 | G24: ='02_Actuals'!G11 | H24: ='02_Actuals'!H11 | I24: ='02_Actuals'!I11 | J24: ='02_Actuals'!J11 | ... N24: ='02_Actuals'!N11
B25: OTIF target | C25: ='01_Assumptions'!C33 | D25: ='01_Assumptions'!D33 | E25: ='01_Assumptions'!E33 | F25: ='01_Assumptions'!F33 | G25: ='01_Assumptions'!G33 | H25: ='01_Assumptions'!H33 | I25: ='01_Assumptions'!I33 | J25: ='01_Assumptions'!J33 | ... N25: ='01_Assumptions'!N33
B26: CCC actual | C26: ='02_Actuals'!C14 | D26: ='02_Actuals'!D14 | E26: ='02_Actuals'!E14 | F26: ='02_Actuals'!F14 | G26: ='02_Actuals'!G14 | H26: ='02_Actuals'!H14 | I26: ='02_Actuals'!I14 | J26: ='02_Actuals'!J14 | ... N26: ='02_Actuals'!N14
B27: CCC target | C27: ='01_Assumptions'!C36 | D27: ='01_Assumptions'!D36 | E27: ='01_Assumptions'!E36 | F27: ='01_Assumptions'!F36 | G27: ='01_Assumptions'!G36 | H27: ='01_Assumptions'!H36 | I27: ='01_Assumptions'!I36 | J27: ='01_Assumptions'!J36 | ... N27: ='01_Assumptions'!N36
B45: Park the reporting month on Assumptions to walk the year. Red tiles are the conversation starters; the heatmap on 03_Scorecard shows whether a miss is a one-month blip.

Sheet 06_Data_Dictionary
B2: Data dictionary
B3: Field definitions so another analyst can inherit the file.
B5: Field | C5: Tab | D5: Definition
B6: Reporting month | C6: 01_Assumptions | D6: 1–12 toggle. Scorecard as-of, YTD, and dashboard INDEX to this month.
B7: Direction H/L/R | C7: 01_Assumptions | D7: H = higher-better, L = lower-better, R = range (hit the plan). Drives RAG.
B8: Amber band | C8: 01_Assumptions | D8: Relative miss still scored Amber. H: actual ≥ target×(1−band). L: actual ≤ target×(1+band).
B9: Green band (R) | C9: 01_Assumptions | D9: For range KPIs only: |actual/target − 1| ≤ green band is Green.
B10: Aggregation | C10: 01_Assumptions | D10: SUM (flows), AVG (rates), LAST (stocks). Used for FY totals and YTD.
B11: Monthly targets | C11: 01_Assumptions | D11: Yellow inputs. Seasonal for revenue/volume/EBITDA; flat policy for OTIF, scrap, DSO, CCC.
B12: FY25 actuals | C12: 01_Assumptions | D12: Prior-year monthly revenue and volume so Trends can show YoY.
B13: Monthly actuals | C13: 02_Actuals | D13: Yellow inputs — the only numbers a controller would paste each month.
B14: YTD actual / target | C14: 02_Actuals | D14: OFFSET/INDEX through the reporting month, using each KPI’s aggregation.
B15: As-of RAG | C15: 03_Scorecard | D15: Green / Amber / Red from actual vs target and the KPI’s direction + bands. Formula, not typed.
B16: Monthly RAG heatmap | C16: 03_Scorecard | D16: Same RAG formula across 12 months. Conditional formatting colors the cells.
... B31: Units | C31: All | D31: Dollars in $000s. Rates in %. Headcount in FTE. Volume in 000 cases. Days in days.
B34: All sample numbers are fictional. Built for a public GitHub portfolio — no employer data.
